{ "book": [
{"cv": "1-1:1", "china": ".", "pinyin": "._", "japan": "人の 手垢や", "hira": "ひとの_てあかや_", "hangul": "사람의 손떼나", "english": "히토노 테아카야", "exp": "."},
{"cv": "1-1:2", "china": ".", "pinyin": ".", "japan": "血が ついた 物に 念願が 込められたら", "hira": "ちが_ついた_ものに_ねんがんが_こめられたら_", "hangul": "피가 묻은 물건에 염원이 들어가면", "english": "치가 츠이타 모노니 넨간가 코매라래타라", "exp": "."},
{"cv": "1-1:3", "china": ".", "pinyin": ".", "japan": "鬼に なるよ", "hira": "おにに_なるよ_", "hangul": "도깨비가 된단다", "english": "오니니 나루요", "exp": "."},
{"cv": "1-1:4", "china": ".", "pinyin": ".", "japan": "多くの 戦場で", "hira": "おおくの_せんじょうで_", "hangul": "수 많은 전쟁터에서", "english": "오오쿠노 센죠우데", "exp": "."},
{"cv": "1-1:5", "china": ".", "pinyin": ".", "japan": "数千の 血を つけた 剣が", "hira": "すうせんの_ちを_つけた_けんが_", "hangul": "수 천의 피가 묻힌 검이", "english": "쑤이센노 치오 츠캐타 캔가", "exp": "."},
{"cv": "1-1:6", "china": ".", "pinyin": ".", "japan": "自分の 主人の 血まで 付けたので 、 ほどであろうか 。 ", "hira": "じぶんの_しゅじんの_ちまで_つけたので_、_ほどであろうか_。__", "hangul": "제 주인의 피까지 묻혔으니 오죽했을까", "english": "지분노 쥬진노 치마데 츠캐타노데 호도데아로우까", "exp": "."},
{"cv": "1-1:7", "china": ".", "pinyin": ".", "japan": "鬼の 花嫁だけ", "hira": "おにの_はなよめだけ_", "hangul": "오직 도깨비 신부만이", "english": "오니노 하나요매다캐", "exp": "."},
{"cv": "1-1:8", "china": ".", "pinyin": ".", "japan": "その 剣を 引くことができる ものだ 。 ", "hira": "その_けんを_ひくことができる_ものだ_。__", "hangul": "그 검을 뽑을 수 있는 사람이다.", "english": "소노 캔오 히쿠코토가데키루 모노다", "exp": "."},
{"cv": "1-1:9", "china": ".", "pinyin": ".", "japan": "剣を 引き抜くなら 、", "hira": "けんを_ひきぬくなら_、__", "hangul": "검을 뽑아내면", "english": "캔오 히키누쿠나라", "exp": "."},
{"cv": "1-1:10", "china": ".", "pinyin": ".", "japan": "無に 戻って 平安になる", "hira": "むに_もどって_へいあんになる_", "hangul": "무로 돌아가 평안하리라", "english": "무니 모돗테 헤이안니나르", "exp": "."},
{"cv": "1-1:11", "china": ".", "pinyin": ".", "japan": "ひどい 信託が ないことが できなかったんだろう", "hira": "ひどい_しんたくが_ないことが_できなかったんだろう_", "hangul": "고약한 신탁이 아닐 수 없었지", "english": "히도이 신타쿠가 나이코토가 데키나캇탄다로우", "exp": "."},
{"cv": "1-1:12", "china": ".", "pinyin": ".", "japan": "そんなに 仏滅で 再び 目を 覚ました 鬼は", "hira": "そんなに_ぶつめつで_ふたたび_めを_さました_おには_", "hangul": "그렇게 불멸로 다시 깨어난 도깨비는", "english": "손나니 부츠매츠데 후타타비 매오 사마시타 오니와", "exp": "."},
{"cv": "1-1:13", "china": ".", "pinyin": ".", "japan": "この 世の 中 どこにでもあり 、 どこにもなく 、 ", "hira": "この_よの_なか_どこにでもあり_、_どこにもなく_、__", "hangul": "이 세상 중 어디에도 있고 어디에도 없고", "english": "코노 요노 나카 도코니데모아리 도코니모나쿠", "exp": "."},
{"cv": "1-1:14", "china": ".", "pinyin": ".", "japan": "今も どこか ~", "hira": "いまも_どこか_~_", "hangul": "지금도 어딘가 ~", "english": "이마모 도코가 ~", "exp": "."},
{"cv": "1-1:15", "china": ".", "pinyin": ".", "japan": "なぜ 笑って 馬鹿よ 腐った ものが", "hira": "なぜ_わらって_ばかよ_くさった_ものが_", "hangul": "왜 웃어 바보야 섞을 것이", "english": "나제 오랏테 바카요 쿠삿타 모노가", "exp": "."},
{"cv": "1-1:16", "china": ".", "pinyin": ".", "japan": "今も どこかで 新婦を 探しているんですが", "hira": "いまも_どこかで_しんぷを_さがしているんですが_", "hangul": "지금도 어딘가에서 신부를 찾고있는데", "english": "이마모 도코카데 신부오 사가시테이른데스가", "exp": "."},
{"cv": "1-1:17", "china": ".", "pinyin": ".", "japan": "その 新婦が まさに 私だと 言う", "hira": "その_しんぷが_まさに_わたしだと_いう_", "hangul": "그 신부가 바로 나다하고 말하려고", "english": "소노 신부가 마사니 와타시다도 이우", "exp": "."},
{"cv": "1-1:18", "china": ".", "pinyin": ".", "japan": "私の こう 見えても 若かった 頃に 男 、 数人も 鳴った 。 ", "hira": "わたしの_こう_みえても_わかった_ころに_おとこ_、_すうにんも_なった_。__", "hangul": "내가 이렇게 보여도 젊었을 때는 남자 여럿 울렸다.", "english": "와타시노 코우 미에테모 와캇타 코로니 오토코 쑤이닌모 낫타", "exp": "."},
{"cv": "1-1:19", "china": ".", "pinyin": ".", "japan": "訳もなく 次に 来て 、 この ばばあ どこへ 行った 驚かすなやな", "hira": "わけもなく_つぎに_きて_、_この_ばばあ_どこへ_いった_おどろかすなやな_", "hangul": "괜히 다음에 왔다가 이 할망구 어디에 갔나 놀라지나마라", "english": "와캐모나쿠 츠기니 키테 코노 바바아 도코에 잇타 오도로카쓰나야나", "exp": "."},
{"cv": "1-1:20", "china": ".", "pinyin": ".", "japan": "うん ~ 羨ましいな", "hira": "うん_~_うらやましいな_", "hangul": "웅 ~ 부럽네 ", "english": "웅 ~ 우라야마시이나", "exp": "."},
{"cv": "1-1:21", "china": ".", "pinyin": ".", "japan": "私は 愚かな ことを しました", "hira": "わたしは_おろかな_ことを_しました_", "hangul": "내가 바보같은 짓을 했다. ", "english": "와타시와 오로카나 코토오 시마시타", "exp": "."},
{"cv": "1-1:22", "china": ".", "pinyin": ".", "japan": "未婚の 母の 前で 言う 自慢が ないのに", "hira": "みこんの_ははの_まえで_いう_じまんが_ないのに_", "hangul": "미혼모 앞에서 자랑할 말은 아닌데", "english": "미콘노 하하노 마에데 이우 지만가 나이노니", "exp": "."},
{"cv": "1-1:23", "china": ".", "pinyin": ".", "japan": "チッ 悪い", "hira": "チッ_わるい_", "hangul": "쳇 나빠", "english": "칫 와루이", "exp": "."},
{"cv": "1-1:24", "china": ".", "pinyin": ".", "japan": "ほうれん草の 価格は 値切ってくれて 、 白菜 価格は 値切ってくれて 私が 何が 悪い ? ", "hira": "ほうれんそうの_かかくは_ねぎってくれて_、_はくさい_かかくは_ねぎってくれて_わたしが_なにが_わるい_?__", "hangul": "시금치 값 깍아주고 배추 값 깍아주고 내가 뭐가 나빠 ?", "english": "후우랜소우노 카카구와 네깃테쿠래테 하쿠사이 카카쿠와 네깃테쿠래테 와타시가 나니가 와르이 ?", "exp": "."},
{"cv": "1-1:25", "china": ".", "pinyin": ".", "japan": "お前 捨てて 逃げた その 奴が 悪い", "hira": "おまえ_すてて_にげた_その_しゃつが_わるい_", "hangul": "널 버리고 도망간 그놈이 나쁘지", "english": "오마에 쓰테테 이개타 소노 샷츠가 와르이", "exp": "."},
{"cv": "1-1:26", "china": ".", "pinyin": ".", "japan": "それはまた 、 そうだね", "hira": "それはまた_、_そうだね_", "hangul": "그건 또 그러네", "english": "오래와마타 소우다네", "exp": "."},
{"cv": "1-1:27", "china": ".", "pinyin": ".", "japan": "ところで その 話 あまりにも 悲しい", "hira": "ところで_その_はなし_あまりにも_かなしい_", "hangul": "그런데 그 이야기 너무 슬프다", "english": "토코로데 소노 하나시 아마리니모 카나시이", "exp": "."},
{"cv": "1-1:28", "china": ".", "pinyin": ".", "japan": "悲しい ことも 多い 。 ", "hira": "かなしい_ことも_おおい_。__", "hangul": "슬플 것도 많다.", "english": "카나시이 코도모 오오이", "exp": "."},
{"cv": "1-1:29", "china": ".", "pinyin": ".", "japan": "ひどく 浪漫的な 呪い じゃないですか 。 ", "hira": "ひどく_ろうまんてきな_のろい_じゃないですか_。__", "hangul": "아주 낭만적인 저주 잖아요.", "english": "히도쿠 로우만데키나 노로이 챠나이데쓰까", "exp": "."},
{"cv": "1-1:30", "china": ".", "pinyin": ".", "japan": "死ぬ ために 新婦を 探すべき だというのが", "hira": "しぬ_ために_しんぷを_さがすべき_だというのが_", "hangul": "죽기 위해서 신부를 찾아야 한다는 것이", "english": "시누 타매니 신부오 사가쓰베키 다토이우노가", "exp": "."},
{"cv": "1-1:31", "china": ".", "pinyin": ".", "japan": "神 悪い", "hira": "かみ_わるい_", "hangul": "신 나쁘다", "english": "카미 와르이", "exp": "."},
{"cv": "1-1:32", "china": ".", "pinyin": ".", "japan": "神は もともと 悪い", "hira": "かみは_もともと_わるい_", "hangul": "신은 원래 못됐어", "english": "카미와 모토모토 와르이", "exp": "."},
{"cv": "1-1:33", "china": ".", "pinyin": ".", "japan": "利己的で 嫉妬 多くて", "hira": "りこてきで_しっと_おおくて_", "hangul": "이기적이고 질투 많고", "english": "리코테키데 싯토 오오쿠데", "exp": "."},
{"cv": "1-1:34", "china": ".", "pinyin": ".", "japan": "自分だけ を 知る 自分だけ", "hira": "じぶんだけ_を_しる_じぶんだけ_", "hangul": "자기만 알아 자기만", "english": "지분다캐 오 시루 지분타캐", "exp": "."},
{"cv": "1-1:35", "china": ".", "pinyin": ".", "japan": "どんな 奴と 同じだね", "hira": "どんな_やつと_おなじだね_", "hangul": "어떤 놈이랑 똑같네", "english": "돈나 야츠토 오나지다네", "exp": "."},
{"cv": "1-1:36", "china": ".", "pinyin": ".", "japan": "ああ もう 行きます 。 たくさん 売って ください 。 ", "hira": "ああ_もう_いきます_。_たくさん_うって_ください_。__", "hangul": "아 이제 갈께요. 많이 파세요.", "english": "아아 모우 이키마쓰. 탁상 웃테 쿠다사이.", "exp": "."},
{"cv": "1-1:37", "china": ".", "pinyin": ".", "japan": "次に 来た 時も ぜひ いて", "hira": "つぎに_きた_ときも_ぜひ_いて_", "hangul": "다음에 왔을 때 꼭 계세요. ", "english": "츠기니 키타 토키모 제히 이테", "exp": "."},
{"cv": "1-1:38", "china": ".", "pinyin": ".", "japan": "生死を 行き来する 瞬間が 来たら", "hira": "せいしを_ゆききする_しゅんかんが_きたら_", "hangul": "생사를 오가는 순간이 오면", "english": "세이시오 유키키쓰루 슌칸가 키타라", "exp": "."},
{"cv": "1-1:39", "china": ".", "pinyin": ".", "japan": "念願を 込めて 、 心から 祈祷する", "hira": "ねんがんを_こめて_、_こころから_きとうする_", "hangul": "염원을 담아 마음속으로 기도해", "english": "넨간오 코매테 코코로카라 키토우쓰루", "exp": "."},
{"cv": "1-1:40", "china": ".", "pinyin": ".", "japan": "もし 、 ある 心の 弱い 神が 聞いて いるのかも 分からない から", "hira": "もし_、_ある_こころの_よわい_かみが_きいて_いるのかも_わからない_から_", "hangul": "혹시 마음이 약한 신이 듣고 있을지도 모르니까", "english": "모시 아르 코코로모 요와이 카미가 키이테 이르노카모 와카라나이 카라 ", "exp": "."},
{"cv": "1-2:1", "china": ".", "pinyin": ".", "japan": "私なら 推薦しない", "hira": "わたしなら_すいせんしない_", "hangul": "나라면 추천하지 않겠어", "english": "와타시나라 쑤이센시나이", "exp": "."},
{"cv": "1-2:2", "china": ".", "pinyin": ".", "japan": "今 家を 出ると 、 今 より もっとできなかった 生活を 暮らす ようになって", "hira": "いま_いえを_でると_、_いま_より_もっとできなかった_せいかつを_くらす_ようになって_", "hangul": "지금 집을 나가면 지금보다 더 못한 생활을 살게 될거야", "english": "이마 이에오 데루토 이마 요리 못토데키나캇타 세이카츠오 쿠라쓰 요우니낫테", "exp": "."},
{"cv": "1-2:3", "china": ".", "pinyin": ".", "japan": "二度と お母さんを 見られなくなるよ 。 ", "hira": "にどと_おかあさんを_みられなくなるよ_。__", "hangul": "두 번 다시 엄마를 못보게 될거고. ", "english": "니도토 오카아상오 미라래나쿠나르요", "exp": "."},
{"cv": "1-2:4", "china": ".", "pinyin": ".", "japan": "あなたが 何だよ . 韓国人 なの ? ", "hira": "あなたが_なんだよ_._かんこくじん_なの_?__", "hangul": "당신 뭐야. 한국인이야 ?", "english": "아나타가 난다요. 한국인이야 ?", "exp": "."},
{"cv": "1-2:5", "china": ".", "pinyin": ".", "japan": "彼 より 複雑な 人だ", "hira": "かれ_より_ふくざつな_ひとだ_", "hangul": "그 보다 복잡한 사람이야", "english": "카래 요리 후쿠자츠카 히토다", "exp": "."},
{"cv": "1-2:6", "china": ".", "pinyin": ".", "japan": "もう あなたの 順番 だよ", "hira": "もう_あなたの_じゅんばん_だよ_", "hangul": "이제 네 차례야", "english": "모우 아나타노 쥰반다요.", "exp": "."},
{"cv": "1-2:7", "china": ".", "pinyin": ".", "japan": "きちんと 話して", "hira": "きちんと_はなして_", "hangul": "또박또박 이야기해", "english": "키찬토 하나시테", "exp": "."},
{"cv": "1-2:8", "china": ".", "pinyin": ".", "japan": "養子縁組 したから 、 あなたは 私の 父とだから よく 飼う ことを", "hira": "ようしえんぐみ_したから_、_あなたは_わたしの_ちちとだから_よく_かう_ことを_", "hangul": "입양했으니 당신은 내 아빠기 때문에 잘 키우라고", "english": "요우시엔구미 시타카라 아나타와 와타시노 치치토다카라 요쿠 카우 코토오", "exp": "."},
{"cv": "1-2:9", "china": ".", "pinyin": ".", "japan": "母にも 話して 助け ほしいと 痛いと", "hira": "ははにも_はなして_たすけ_ほしいと_いたいと_", "hangul": "엄마한테도 말해 도와달라고 아프다고", "english": "하하니모 하나시테 타시캐 호시이토 이타이토", "exp": "."},
{"cv": "1-2:10", "china": ".", "pinyin": ".", "japan": "どんな 馬鹿な 話だ", "hira": "どんな_ばかな_はなしだ_", "hangul": "무슨 바보같은 소리야.", "english": "돈나 바카나 하나시타", "exp": "."},
{"cv": "1-2:11", "china": ".", "pinyin": ".", "japan": "どいて そうように 引いては 死なず 、 手だけ 使えない ことになって 参考にして", "hira": "どいて_そうように_ひいては_しなず_、_てだけ_つかえない_ことになって_さんこうにして_", "hangul": "그렇게 그어서는 죽지 않고 손만 못쓰게 되니까 참고하고", "english": "도이테 소우요우니 히이테와 시나즈. 테다캐 츠카에나이 코토이낫테. 산코우니시테.", "exp": "."},
{"cv": "1-2:12", "china": ".", "pinyin": ".", "japan": "あなた 誰 ? ", "hira": "あなた_だれ_?__", "hangul": "당신 누구야 ?", "english": "아나타 다래 ?", "exp": "."},
{"cv": "1-2:13", "china": ".", "pinyin": ".", "japan": "目 避けずに きちんと できる ? ", "hira": "め_さけずに_きちんと_できる_?__", "hangul": "눈 피하지 말고 또박또박 할 수 있겠어 ?", "english": "매 사캐즈니 키친토 데키루 ?", "exp": "."},
{"cv": "1-2:14", "china": ".", "pinyin": ".", "japan": "そうして 迎え 、 死ねば あなたが 責任を 取るの ? ", "hira": "そうして_むかえ_、_しねば_あなたが_せきにんを_とるの_?__", "hangul": "그렇게 했다가, 죽으면 당신이 책임 질거야 ?", "english": "소우시테 무카에, 시누바 아나타가 세키닌오 토루노 ?", "exp": "."},
{"cv": "1-2:15", "china": ".", "pinyin": ".", "japan": "それで 肋骨 折って くれたんじゃん 。 ", "hira": "それで_ろっこつ_おって_くれたんじゃん_。__", "hangul": "그래서 갈비뼈 부러뜨려 줬잖아.", "english": "소래데 롯코츠 옷테 쿠래탄쟌", "exp": "."},
{"cv": "1-2:16", "china": ".", "pinyin": ".", "japan": "これは 弁当 . 話 終わったら 学校 行け . 数学の 問題 17 番の 答えは 2 ではなく 、 4 は これ 一つ 間違ってさ", "hira": "これは_べんとう_._はなし_おわったら_がっこう_いけ_._すうがくの_もんだい_じゅうしちにち_ばんの_こたえは_に_ではなく_、_し_は_これ_ひとつ_まちがってさ_", "hangul": "이건 도시락. 이야기 끈났으면 학교에 가. 수학 문제 17번 정답은 2가 아니라 4야. 그거 하나 틀렸더군. ", "english": "코래와 벤토우. 하나시 오왓타라 갓코우 이캐. 쑤우가쿠노 몬타이 쥬우시치니치 반노 코타에와 이 데와나쿠 시와 코래 히토츠 마치갓테사", "exp": "."},
{"cv": "1-2:17", "china": ".", "pinyin": ".", "japan": "あなた 一体 誰だ", "hira": "あなた_いったい_だれだ_", "hangul": "당신 도대체 누구야", "english": "아나타 잇타이 다래다", "exp": "."},
{"cv": "1-3:1", "china": ".", "pinyin": ".", "japan": "彼は ... 水で 火で 風で あり . 光で あり 、 闇で ある", "hira": "かれは_..._みずで_ひで_かぜで_あり_._ひかりで_あり_、_やみで_ある_", "hangul": "그는 물이며 불이며 바람이다. 빛이며 어둠이다.", "english": "카래와 ... 미즈데 히데 카제데 하리. 히카리데 아리. 야미데 아르.", "exp": "."},
{"cv": "1-3:2", "china": ".", "pinyin": ".", "japan": "そして 一時 . 人間 だった 。 ", "hira": "そして_いちじ_._にんげん_だった_。__", "hangul": "그리고 한 때 인간 있었다. ", "english": "소시테 이치지. 닌갠 닷타.", "exp": "."},
{"cv": "1-3:3", "china": ".", "pinyin": ".", "japan": "民たちは 彼を 神と 呼んだ 。 ", "hira": "たみたちは_かれを_かみと_よんだ_。__", "hangul": "백성들은 그를 신이라 불렀다.", "english": "타미타치와 카래오 카미토 욘다.", "exp": "."},
{"cv": "1-3:4", "china": ".", "pinyin": ".", "japan": "真っ赤な 血を かぶったまま 敵を 切って 進む . 彼は 文字通りの 武臣 、 だった 。 ", "hira": "まっかな_ちを_かぶったまま_てきを_きって_すすむ_._かれは_もじどおりの_ぶしん_、_だった_。__", "hangul": "시뻘건 피를 뒤집어쓰고 적으로 베러 나가는 . 그는 문자 그대로 무신 이었다. ", "english": "맛카나 치오 카붓타마마 테키오 킷테 쓰쓰무. 개래와 모지도오리노 부신 닷타.", "exp": "."},
{"cv": "1-3:5", "china": ".", "pinyin": ".", "japan": "金信 将軍 万歳 ~", "hira": "キムシン_しょうぐん_ばんざい_~_", "hangul": "김신 장군 만세", "english": "키무신 쇼군 반자이 ", "exp": "."},
{"cv": "1-3:6", "china": ".", "pinyin": ".", "japan": "ドアを 開けろ 凱旋将軍 、 金信 将軍 だ 。 ", "hira": "ドアを_あけろ_がいせんしょうぐん._、_キムシン_しょうぐん_だ_。__", "hangul": "문을 열어라 개선장군 김신 장군이시다.", "english": "도아오 아캐로 가이센쇼군 키무신 쇼군 다", "exp": "."},
{"cv": "1-3:7", "china": ".", "pinyin": ".", "japan": "キムシンは 軍装を 解いて 命令を 受けなさい", "hira": "キムシンは_ぐんそうを_といて_めいれいを_うけなさい_", "hangul": "김신은 군장을 풀고 명령을 받으라", "english": "키무신와 군소우오 토이테 매이래이오 우캐나사이", "exp": "."},
{"cv": "1-3:8", "china": ".", "pinyin": ".", "japan": "はいこいつ 再び しゃべって みなさい", "hira": "はいこいつ_ふたたび_しゃべって_みなさい_", "hangul": "네 이놈 다시 지껄여 보아라", "english": "하이코이츠 후타타비 샤벳테 미나사이", "exp": "."},
{"cv": "1-3:9", "china": ".", "pinyin": ".", "japan": "從 7 品の 別荘 やつが", "hira": "じゅう_なな_ひんの_べっそう_やつが_", "hangul": "종 7품 별장 놈이", "english": "쥬 나나 힌노 벳소우 야츠가", "exp": "."},
{"cv": "1-3:10", "china": ".", "pinyin": ".", "japan": "あえて 上将軍の 尊名を", "hira": "あえて_じょうしょうぐんの_そんめいを_", "hangul": "감히 상장군의 존명을", "english": "아에테 죠우쇼우군노 손매이오", "exp": "."},
{"cv": "1-3:11", "china": ".", "pinyin": ".", "japan": "歸還軍の 班主 キムシン", "hira": "きかんぐんの_はんしゅ_キムシン_", "hangul": "귀환군의 반주 김신", "english": "키칸군노 한슈 키무신", "exp": "."},
{"cv": "1-3:12", "china": ".", "pinyin": ".", "japan": "軍装を 解いて", "hira": "ぐんそうを_といて_", "hangul": "군장을 풀고", "english": "군소우오 토이테", "exp": "."},
{"cv": "1-3:13", "china": ".", "pinyin": ".", "japan": "聞いた 待ちなさい", "hira": "きいた_まちなさい_", "hangul": "들었다 기다려라", "english": "키이타 마치나사이", "exp": "."},
{"cv": "1-3:14", "china": ".", "pinyin": ".", "japan": "できたか 。 ", "hira": "できたか_。__", "hangul": "되었느냐", "english": "데키타까", "exp": "."},
{"cv": "1-3:15", "china": ".", "pinyin": ".", "japan": "帯域罪人 キムシンは 剣を 咥えて ひざまずいて 王命を 奉ずる", "hira": "たいいきつみびと_キムシンは_けんを_くわえて_ひざまずいて_おうめいを_ほうずる_", "hangul": "대역죄인 김신은 검을 물고 무릎을 꿇고 왕명을 받들라", "english": "타이이키츠미비토 키무신와 캔오 쿠와에테 히자마즈이테 오우매이오 호우즈루", "exp": "."},
{"cv": "1-3:16", "china": ".", "pinyin": ".", "japan": "舌を 抜いて しまいぞ", "hira": "したを_ぬいて_しまいぞ_", "hangul": "혀를 뽑아 버릴라", "english": "시타오 누이테 시마이조", "exp": "."},
{"cv": "1-3:17", "china": ".", "pinyin": ".", "japan": "帯域罪人 とは 狂するのか 狂ったのか", "hira": "たいいきつみびと_とは_きょうするのか_くるったのか_", "hangul": "대역죄인이라 미쳤는냐 돌았느냐", "english": "타이이키츠미비토 토와 쿄우쓰로노까 쿠릇타노까", "exp": "."},
{"cv": "1-3:18", "china": ".", "pinyin": ".", "japan": "帯域罪人 キムシンは 剣を くわえて ひざまずいて", "hira": "たいいきつみびと_キムシンは_けんを_くわえて_ひざまずいて_", "hangul": "대역죄인 김신은 검을 물고 무릎을 꿇고", "english": "타이이키츠미비토 키무신와 캔오 쿠와에테 하자마즈이테", "exp": "."},
{"cv": "1-3:19", "china": ".", "pinyin": ".", "japan": "陛下に 会いたい 道を 開く", "hira": "へいかに_あいたい_みちを_ひらく_", "hangul": "폐하를 뵙고자한다 길을 열어라", "english": "헤이카니 하이타이 미치오 히라쿠", "exp": "."},
{"cv": "1-3:20", "china": ".", "pinyin": ".", "japan": "罪人 キムシンは", "hira": "つみびと_キムシンは_", "hangul": "죄인 김신은", "english": "츠미비토 기무신와", "exp": "."},
{"cv": "1-3:21", "china": ".", "pinyin": ".", "japan": "阻止したら 必ず 死ぬ ことだ ", "hira": "そししたら_かならず_しぬ_ことだ__", "hangul": "저지하면 반드시 죽을 것이다", "english": "소시시타라 카나라즈 시누 코토다", "exp": "."},
{"cv": "1-3:22", "china": ".", "pinyin": ".", "japan": "道を 開く", "hira": "みちを_ひらく_", "hangul": "길을 터라", "english": "미치오 히라쿠", "exp": "."},
{"cv": "1-3:23", "china": ".", "pinyin": ".", "japan": "はいこいつら ただ 主君の 名前で 三昼夜を 戦った", "hira": "はいこいつら_ただ_しゅくんの_なまえで_みっつちゅうやを_たたかった_", "hangul": "네 이놈들 오직 주군의 이름으로 삼일 밤낮을 싸웠다.", "english": "하이코이츠라 타다 슈군노 나마에데 밋츠츄야오 타타캇타", "exp": "."},
{"cv": "1-3:24", "china": ".", "pinyin": ".", "japan": "その 生き 地獄で 生きて 帰ってくる 道だという 言葉だ はい 、 お前たちが あえて お前たちが", "hira": "その_いき_じごくで_いきて_かえってくる_みちだという_ことばだ_はい_、_おまえたちが_あえて_おまえたちが_", "hangul": "그 생지옥에서 살아서 돌아오는 길이란 말이다. 네 놈들이 감히 네 놈들이", "english": "소노 이키 지오쿠데 이키테 카엣테쿠루 미치다토이우 코토바다 하이 . 오마에타치가 아에테 오마에타치가", "exp": "."},
{"cv": "1-3:25", "china": ".", "pinyin": ".", "japan": "城門を 開けなさい", "hira": "じょうもんを_あけなさい_", "hangul": "성문을 열어라", "english": "죠몬오 아캐나사이", "exp": "."},
{"cv": "1-3:26", "china": ".", "pinyin": ".", "japan": "彼らの そばを 守りなさい すぐ 行って 来てね", "hira": "かれらの_そばを_まもりなさい_すぐ_いって_きてね_", "hangul": "그들 곁을 지켜라 금방 갔다 오마", "english": "코래라노 소바오 마모리나사이 쓰구 잇테 키테네", "exp": "."},
{"cv": "1-3:27", "china": ".", "pinyin": ".", "japan": "民の 上に 王 王 上に 神 その 神が 、 金信 を 指すします 。 ", "hira": "たみの_うえに_おう_おう_うえに_かみ_その_かみが_、_キムシン_を_さすします_。__", "hangul": "백성 위에 왕. 왕위에 신. 그 신이 김신을 가리킨다고 합니다. ", "english": "타미노 우에니 오우 . 오우 우에니 카미 . 소노 카미가 키무신 오 사쓰시마쓰", "exp": "."},
{"cv": "1-3:28", "china": ".", "pinyin": ".", "japan": "あれの 果てしない 勝利の 来報が 民を 幻惑して あれの 権勢が 重ねて 王室を 嘲弄したら 国法に 厳しく 治めてください", "hira": "あれの_はてしない_しょうりの_らいほうが_たみを_げんわくして_あれの_けんせいが_かさねて_おうしつを_ちょうろうしたら_こくほうに_きびしく_おさめてください_", "hangul": "저자의 끝없는 승리의 보고가 백성을 현혹시키고 저자의 권세가 거듭 왕실을 조롱하니 국법으로 엄하게 다스리소서", "english": "아래노 하데시나이 쇼우리노 라이보우가 타미오 갠와쿠시테 아래노 캔세가 카사네테 오우시츠오 쵸우로우시타라 코쿠호우니 키비시쿠 오사매루쿠다사이", "exp": "."},
{"cv": "1-3:29", "china": ".", "pinyin": ".", "japan": "彼は 敵の 刃を 正確に みたが 自分に 向けた 幼い 王の 嫉妬と 不安は 見る ことが できなかった", "hira": "かれは_てきの_はを_せいかくに_みたが_じぶんに_むけた_おさない_おうの_しっとと_ふあんは_みる_ことが_できなかった_", "hangul": "그는 적의 칼날은 정확하게 보면서 자신을 향한 어린 왕의 질투와 불안은 보지 못했다. ", "english": "카래와 테키노 하오 세카쿠니 미타가 지분니 무캐타 오사나이 오우노 싯토토 후안와 미르 코토가 데키나캇타", "exp": "."},
{"cv": "1-3:30", "china": ".", "pinyin": ".", "japan": "それが 自分に 向けた 最も 鋭い 刃 だった ことを ", "hira": "それが_じぶんに_むけた_もっとも_するどい_は_だった_ことを__", "hangul": "그것이 자신을 향한 가장 날카로운 칼날임을", "english": "소래가 지분니 무캐타 못토모 쓰로도이 하 닷타 코토오", "exp": "."},
{"cv": "1-3:31", "china": ".", "pinyin": ".", "japan": "彼は 知らなかった", "hira": "かれは_しらなかった_", "hangul": "그는 알지 못했다.", "english": "카래와 시라나캇타", "exp": "."},
{"cv": "1-3:32", "china": ".", "pinyin": ".", "japan": "本当に こんなにまで しているのですか ? ", "hira": "ほんとうに_こんなにまで_しているのですか_?__", "hangul": "정녕 이렇게까지 하시는 것입니까 ?", "english": "혼토우니 콘나니마데 시테이르노데쓰까 ?", "exp": "."},
{"cv": "1-3:33", "china": ".", "pinyin": ".", "japan": "だから これ 以上は 来るな 止まりなさい 、 それが 何でも 止めなさい", "hira": "だから_これ_いじょうは_くるな_とどまりなさい_、_それが_なんでも_とどめなさい_", "hangul": "그러니 이 이상은 오지마라. 멈추어라. 그것이 무엇이든 멈추어라.", "english": "다카라 코래 이죠우와 쿠루나. 토도마리나사이. 소래가 난데모 토도매나사이.", "exp": "."},
{"cv": "1-3:34", "china": ".", "pinyin": ".", "japan": "その 場に 止まって 逆賊と 死になさい それじゃ 、 あなたを 除いた すべての 人を 生かすつもりだ", "hira": "その_ばに_とどまって_ぎゃくぞくと_しになさい_それじゃ_、_あなたを_のぞいた_すべての_ひとを_いかすつもりだ_", "hangul": "거기서 멈추어 역적으로 죽어라. 그러면 너를 빼고 모든 사람이 살게될 것이다.", "english": "소노 바니 토오맛테 캭쿠도쿠토 시니나사이. 소랴쟈 아나타노 노조이타 스베테노 히토오 이카쓰츠모리다.", "exp": "."},
{"cv": "1-3:35", "china": ".", "pinyin": ".", "japan": "しかし 一歩で ももっと 近付いて 来たら 貴様の 足取り 一つ 視線 一度に 全てを 殺して 貴様の 足の 前に 敷いて くれるだろう 。 ", "hira": "しかし_いっぽで_ももっと_ちかづくいて_きたら_きさまの_あしどり_ひとつ_しせん_いちどに_すべてを_ころして_きさまの_あしの_まえに_しいて_くれるだろう_。__", "hangul": "그러나 한 걸음 더 나오면 네 놈의 발걸음 하나 시선 하나에 전부를 죽여서 네놈의 발치에 깔아 줄 것이다.", "english": "시카시 싯포데 모못토 치카즈쿠이테 키다라 키사마노 아시도리 히토츠 시센 이치도니 쓰베테오 코로시테 키사마노 아시노 마에니 시이테 쿠래르다로우.", "exp": "."},
{"cv": "1-3:36", "china": ".", "pinyin": ".", "japan": "行って ください 将軍", "hira": "いって_ください_しょうぐん_", "hangul": "가세요 장군", "english": "잇테 쿠다사이 쇼군", "exp": "."},
{"cv": "1-3:36", "china": ".", "pinyin": ".", "japan": "私は 大丈夫です", "hira": "わたしは_だいじょうぶです_", "hangul": "저는 괜찮습니다.", "english": "와타시와 다이죠부데쓰", "exp": "."},
{"cv": "1-3:37", "china": ".", "pinyin": ".", "japan": "僕は … ママ 私は", "hira": "ぼくは_…_ママ_わたしは_", "hangul": "저는 ... 마마 나는", "english": "보쿠와 ... 마마 와타시와", "exp": "."},
{"cv": "1-3:38", "china": ".", "pinyin": ".", "japan": "知っています", "hira": "しっています_", "hangul": "압니다.", "english": "싯테이마쓰", "exp": "."},
{"cv": "1-3:39", "china": ".", "pinyin": ".", "japan": "本当に 皆 知っています", "hira": "ほんとうに_みな_しっています_", "hangul": "정말 다 압니다.", "english": "혼토우니 미나 싯테이마쓰", "exp": "."},
{"cv": "1-3:40", "china": ".", "pinyin": ".", "japan": "もし これが 最後なら 、 これも 私の 運命 なんです", "hira": "もし_これが_最後なら_、_これも_わたしの_うんめい_なんです_", "hangul": "혹시 그것이 마지막이면 그것도 제 운명입니다. ", "english": "모시 코래가 사이고나라. 코래모 와타시노 운매이 난데쓰.", "exp": "."},
{"cv": "1-3:41", "china": ".", "pinyin": ".", "japan": "だから 行って ください 止まらず 陛下に 行って ください 。 将軍 ", "hira": "だから_いって_ください_とどまらず_へいかに_いって_ください_。_しょうぐん__", "hangul": "그러니 가십시요. 멈추지말고 폐하께 가세요. 장군", "english": "다카라 잇테 구다사이 토도마라즈 헤이카니 잇테 쿠다사이 쇼군", "exp": "."},
{"cv": "1-3:42", "china": ".", "pinyin": ".", "japan": "逆謀だ あの 家の 誰の 息も つけておきてはいけない 御命だ", "hira": "ぎゃくぼうだ_あの_いえの_だれの_いきも_つけておきてはいけない_おめいだ_", "hangul": "역모다. 저 집안의 누구도 숨이 붙어 있지 말게 하라. 어명이다.", "english": "갸쿠호우다 아노 이에노 다래노 이키모 츠캐테오키테와이캐나이 오매이다", "exp": "."},
{"cv": "1-3:43", "china": ".", "pinyin": ".", "japan": "止まりなさい", "hira": "とどまりなさい_", "hangul": "멈추어라.", "english": "토도마리나사이", "exp": "."},
{"cv": "1-3:44", "china": ".", "pinyin": ".", "japan": "何を するか 罪人を ひざまずいて", "hira": "なにを_するか_つみびとを_ひざまずいて_", "hangul": "뭐 하느냐 죄인을 꿇려라.", "english": "나니오 쓰루까 츠미비토오 히자마즈이테", "exp": "."},
{"cv": "1-3:45", "china": ".", "pinyin": ".", "japan": "将軍", "hira": "しょうぐん_", "hangul": "장군", "english": "쇼군", "exp": "."},
{"cv": "1-3:46", "china": ".", "pinyin": ".", "japan": "陛下 どうしてこんなですか ? 天が 怖くない ですか ? ", "hira": "へいか_どうしてこんなですか_?_てんが_こわくない_ですか_?__", "hangul": "폐하 어찌 어러십니까? 하늘이 두렵지 않으십니까?", "english": "헤이카 도우시테콘나데쓰까 ? 텐가 코와쿠나이 데스까 ?", "exp": "."},
{"cv": "1-3:47", "china": ".", "pinyin": ".", "japan": "天は いつ あなたの 肩を 持つ やるか？", "hira": "てんは_いつ_あなたの_かたを_もつ_やるか？_", "hangul": "하늘이 언제 네놈들 편을 들겠느냐 ?", "english": "텐와 이츠 아나타노 가와오 키쿠노 야루까 ?", "exp": "."},
{"cv": "1-3:48", "china": ".", "pinyin": ".", "japan": "罪人の 目が 炯炯 したら 御心が 乱れている 必ず 斬せよ", "hira": "つみびとの_めが_けいけい_したら_みこころが_みだれている_かならず_ざんせよ_", "hangul": "죄인의 눈이 형형하니 어심이 어지럽다 반드시 참하라", "english": "츠미미토노 매가 캐캐시타라 미코코로가 미다래테이르 카나라즈 잔세요.", "exp": "."},
{"cv": "1-3:49", "china": ".", "pinyin": ".", "japan": "君の ことではない", "hira": "きみの_ことではない_", "hangul": "그대이 일이 아니다. ", "english": "키미노 코토데와나이", "exp": "."},
{"cv": "1-3:50", "china": ".", "pinyin": ".", "japan": "将軍 将軍 将軍 将軍", "hira": "しょうぐん_しょうぐん_しょうぐん_しょうぐん_", "hangul": "장군 장군 장군 장군", "english": "쇼군 쇼군 쇼군 쇼군", "exp": "."},
{"cv": "1-3:51", "china": ".", "pinyin": ".", "japan": "最後を .... 君に お願い したいんだ", "hira": "さいごを_...._きみに_おねがい_したいんだ_", "hangul": "최후를 ... 자네에게 부탁하고 싶은데.", "english": "사이고오 ... 키미니 오네가이 시타인다", "exp": "."},
{"cv": "1-3:52", "china": ".", "pinyin": ".", "japan": "上将軍の 命を 受けます", "hira": "じょうしょうぐんの_いのちを_うけます_", "hangul": "상장군의 명을 받듭니다.", "english": "죠우쇼우군노 이노치오 우캐마쓰", "exp": "."},
{"cv": "1-3:53", "china": ".", "pinyin": ".", "japan": "許してください", "hira": "ゆるしてください_", "hangul": "용서하십시요.", "english": "유르시테쿠다사이", "exp": "."},
{"cv": "1-3:54", "china": ".", "pinyin": ".", "japan": "すぐ 追い つく 伺いします 。 ", "hira": "すぐ_おい_つく_うかがいします_。__", "hangul": "곧 따라 가서 뵙겠습니다.", "english": "쓰구 오이 츠쿠 우카가이시마쓰", "exp": "."},
{"cv": "1-3:55", "china": ".", "pinyin": ".", "japan": "その 誰も 反逆罪人の 遺体を 収拾 してはいけない 。 ", "hira": "その_だれも_はんぎゃくつみびとの_いたいを_しゅうしゅう_してはいけない_。__", "hangul": "그 누구도 반역죄인의 시신을 수습하지 말라", "english": "소노 다래모 한갸쿠츠미비토노 이타이오 슈슈 시테와이캐나이", "exp": "."},
{"cv": "1-3:56", "china": ".", "pinyin": ".", "japan": "野原に 放置して 野生の 動物と 鳥類は 生き 物の えさとして おきなさい", "hira": "のはらに_ほうちして_やせいの_どうぶつと_ちょうるいは_いき_ものの_えさとして_おきなさい_", "hangul": "들판에 내버려두어 야생동물이나 새들의 먹이가 되게하라", "english": "노하라니 호우치시테 야세이노 도우부츠토 쵸우루이와 이키 모노노 체사토시테 오키나사이", "exp": "."},
{"cv": "1-3:57", "china": ".", "pinyin": ".", "japan": "禽獣の 飢えを 癒す ちょうど その 程度が あいつの 価値だ 御命だ ", "hira": "きんじゅうの_うえを_いやす_ちょうど_その_ていどが_あいつの_かちだ_おめいだ__", "hangul": "금수의 허기를 달래는 딱 그 정도가 저자의 가치다. 어명이다.", "english": "킨죠우노 우에오 이야쓰 쵸우도 소노 데이토가 아이츠노 카치다 오매이다", "exp": "."},
{"cv": "1-3:58", "china": ".", "pinyin": ".", "japan": "その 誰にも 祈るな 。 ", "hira": "その_だれにも_いのるな_。__", "hangul": "그 누구에게도 빌지말라", "english": "소노 다래니모 이노르나", "exp": "."},
{"cv": "1-3:59", "china": ".", "pinyin": ".", "japan": "神は 聞いて いないため 、 ", "hira": "かみは_きいて_いないため_、__", "hangul": "신은 듣고 있지 않으니", "english": "카미와 키이테 이나이타매", "exp": "."},
{"cv": "1-3:60", "china": ".", "pinyin": ".", "japan": "一日中 一番 朗らかな 午時", "hira": "いちにちじゅう_いちばん_ほがらかな_ごじ_", "hangul": "하루 중 가장 화창한 오시", "english": "이치니치쥬 이찌방 호가라가나 고지", "exp": "."},
{"cv": "1-3:61", "china": ".", "pinyin": ".", "japan": "彼は 自分が 守っていた 主君の 刃に 死んだ 。 ", "hira": "かれは_じぶんが_まもっていた_しゅくんの_はに_しんだ_。__", "hangul": "그는 자신이 지키던 주군의 칼날에 죽었다. ", "english": "카래와 지분가 마못테이타 슈군노 하니 신다", "exp": "."},
{"cv": "1-4:1", "china": ".", "pinyin": ".", "japan": "アシ この ような 狂った こいつが 目が 何の 装飾 ですか ? 死にたいのか", "hira": "アシ_この_ような_くるった_こいつが_めが_なにの_そうしょく_ですか_?_しにたいのか_", "hangul": "아 씨 이런 미친 새끼가 눈은 무슨 장식이야 ? 죽고싶어 ?", "english": "아시 코노 요우나 쿠룻타 코이츠가 매가 나니노 소우쇼쿠 데쓰까 ? 시니타이노까 ", "exp": "."},
{"cv": ".", "china": ".", "pinyin": ".", "japan": ".", "hira": ".", "hangul": ".", "english": ".", "exp": "."}
]}