{ "book": [

{"hanja": "", "um": ""},
{"hanja": "", "um": ""},
{"hanja": "", "um": ""},
{"hanja": "", "um": ""},
{"hanja": "", "um": ""},
{"hanja": "", "um": ""},
{"hanja": "", "um": ""},
{"hanja": "", "um": ""},
{"hanja": "", "um": ""},
{"hanja": "", "um": ""},
{"hanja": "", "um": ""},
{"hanja": "", "um": ""},
{"hanja": "", "um": ""},
{"hanja": "", "um": ""},
{"hanja": "", "um": ""},
{"hanja": "", "um": ""},
{"hanja": "", "um": ""},
{"hanja": "", "um": ""},
{"hanja": "", "um": ""},
{"hanja": "", "um": ""},
{"hanja": "", "um": ""},
{"hanja": "", "um": ""},
{"hanja": "", "um": ""},
{"hanja": "", "um": ""},
{"hanja": "", "um": ""},
{"hanja": "", "um": ""},
{"hanja": "", "um": ""},
{"hanja": "", "um": ""},
{"hanja": "", "um": ""},
{"hanja": "", "um": ""},
{"hanja": "", "um": ""},
{"hanja": "", "um": ""},
{"hanja": "", "um": ""},
{"hanja": "", "um": ""},
{"hanja": "", "um": ""},
{"hanja": "", "um": ""},
{"hanja": "", "um": ""},
{"hanja": "", "um": ""},
{"hanja": "", "um": ""},
{"hanja": "", "um": ""},
{"hanja": "", "um": ""},
{"hanja": "", "um": ""},
{"hanja": "", "um": ""},
{"hanja": "", "um": ""},
{"hanja": "", "um": ""},
{"hanja": "", "um": ""},
{"hanja": "", "um": ""},
{"hanja": "", "um": ""},
{"hanja": "", "um": ""},
{"hanja": "", "um": ""},
{"hanja": "", "um": ""},
{"hanja": "", "um": ""},
{"hanja": "", "um": ""},
{"hanja": "", "um": ""},
{"hanja": "", "um": ""},
{"hanja": "", "um": ""},
{"hanja": "", "um": ""},
{"hanja": "", "um": ""},
{"hanja": "", "um": ""},
{"hanja": "", "um": ""},
{"hanja": "", "um": ""},
{"hanja": "", "um": ""},
{"hanja": "", "um": ""},
{"hanja": "", "um": ""},
{"hanja": "", "um": ""},
{"hanja": "", "um": ""},
{"hanja": "", "um": ""},
{"hanja": "", "um": ""},
{"hanja": "", "um": ""},
{"hanja": "", "um": ""},
{"hanja": "", "um": ""},
{"hanja": "", "um": ""},
{"hanja": "", "um": ""},
{"hanja": "", "um": ""},
{"hanja": "", "um": ""},
{"hanja": "", "um": ""},
{"hanja": "", "um": ""},
{"hanja": "", "um": ""},
{"hanja": "", "um": ""},
{"hanja": "", "um": ""},
{"hanja": "", "um": ""},
{"hanja": "", "um": ""},
{"hanja": "", "um": ""},
{"hanja": "", "um": ""},
{"hanja": "", "um": ""},
{"hanja": "", "um": ""},
{"hanja": "", "um": ""},
{"hanja": "聪", "um": "cōng"},
{"hanja": "拣", "um": "jiǎn"},
{"hanja": "觉", "um": "jué"},
{"hanja": "槁", "um": "gǎo"},
{"hanja": "软", "um": "ruǎn"},
{"hanja": "刮", "um": "guā"},
{"hanja": "剃", "um": "tì"},
{"hanja": "即", "um": "jí"},
{"hanja": "遂", "um": "suì"},
{"hanja": "圆", "um": "yuán"},
{"hanja": "术", "um": "shù"},
{"hanja": "饱", "um": "bǎo"},
{"hanja": "焦", "um": "jiāo"},
{"hanja": "佳", "um": "jiā"},
{"hanja": "穗", "um": "suì"},
{"hanja": "陋", "um": "lòu"},
{"hanja": "荻", "um": "dí"},
{"hanja": "芦", "um": "lú"},
{"hanja": "挂", "um": "guà"},
{"hanja": "斩", "um": "zhǎn"},
{"hanja": "筐", "um": "kuāng"},
{"hanja": "拐", "um": "guǎi"},
{"hanja": "牢", "um": "láo"},
{"hanja": "职", "um": "zhí"},
{"hanja": "芽", "um": "yá"},
{"hanja": "闷", "um": "mēn"},
{"hanja": "府", "um": "fǔ"},
{"hanja": "膳", "um": "shàn"},
{"hanja": "政", "um": "zhèng"},
{"hanja": "监", "um": "jiàn"},
{"hanja": "狱", "um": "yù"},
{"hanja": "囚", "um": "qiú"},
{"hanja": "喊", "um": "hǎn"},
{"hanja": "弄", "um": "nòng"},
{"hanja": "概", "um": "gài"},
{"hanja": "务", "um": "wù"},
{"hanja": "伺", "um": "sì"},
{"hanja": "遮", "um": "zhē"},
{"hanja": "寡", "um": "guǎ"},
{"hanja": "遗", "um": "yí"},
{"hanja": "复", "um": "fù"},
{"hanja": "卫", "um": "wèi"},
{"hanja": "护", "um": "hù"},
{"hanja": "悲", "um": "bēi"},
{"hanja": "麻", "um": "má"},
{"hanja": "腰", "um": "yāo"},
{"hanja": "碎", "um": "suì"},
{"hanja": "捡", "um": "jiǎn"},
{"hanja": "染", "um": "rǎn"},
{"hanja": "讲", "um": "jiǎng"},
{"hanja": "药", "um": "yào"},
{"hanja": "夥", "um": "huǒ"},
{"hanja": "丢", "um": "diū"},
{"hanja": "禾", "um": "hé"},
{"hanja": "越", "um": "yuè"},
{"hanja": "叠", "um": "dié"},
{"hanja": "桑", "um": "sāng"},
{"hanja": "续", "um": "xù"},
{"hanja": "京", "um": "jīng"},
{"hanja": "番", "um": "fān"},
{"hanja": "欣", "um": "xīn"},
{"hanja": "温", "um": "wēn"},
{"hanja": "朔", "um": "shuò"},
{"hanja": "坦", "um": "tǎn"},
{"hanja": "玻", "um": "bō"},
{"hanja": "螅", "um": "xī"},
{"hanja": "毯", "um": "tǎn"},
{"hanja": "啊", "um": "ǎ"},
{"hanja": "熟", "um": "shú"},
{"hanja": "春", "um": "chūn"},
{"hanja": "台", "um": "tái"},
{"hanja": "墓", "um": "mù"},
{"hanja": "碑", "um": "bēi"},
{"hanja": "统", "um": "tǒng"},
{"hanja": "恒", "um": "héng"},
{"hanja": "悯", "um": "mǐn"},
{"hanja": "婆", "um": "pó"},
{"hanja": "艰", "um": "jiān"},
{"hanja": "段", "um": "duàn"},
{"hanja": "奠", "um": "diàn"},
{"hanja": "波", "um": "bō"},
{"hanja": "周", "um": "zhōu"},
{"hanja": "朵", "um": "duǒ"},
{"hanja": "裳", "um": "cháng"},
{"hanja": "换", "um": "huàn"},
{"hanja": "麽", "um": "mó"},
{"hanja": "妓", "um": "jì"},
{"hanja": "稀", "um": "xī"},
{"hanja": "臭", "um": "chòu"},
{"hanja": "疼", "um": "téng"},
{"hanja": "依", "um": "yī"},
{"hanja": "货", "um": "huò"},
{"hanja": "嫁", "um": "jià"},
{"hanja": "睦", "um": "mù"},
{"hanja": "诈", "um": "zhà"},
{"hanja": "诡", "um": "guǐ"},
{"hanja": "丑", "um": "chǒu"},
{"hanja": "恼", "um": "nǎo"},
{"hanja": "忿", "um": "fèn"},
{"hanja": "议", "um": "yì"},
{"hanja": "污", "um": "wū"},
{"hanja": "聘", "um": "pìn"},
{"hanja": "蜜", "um": "mì"},
{"hanja": "甜", "um": "tián"},
{"hanja": "系", "um": "xì"},
{"hanja": "辱", "um": "rǔ"},
{"hanja": "玷", "um": "diàn"},
{"hanja": "淫", "um": "yín"},
{"hanja": "疏", "um": "shū"},
{"hanja": "娇", "um": "jiāo"},
{"hanja": "幼", "um": "yòu"},
{"hanja": "够", "um": "gòu"},
{"hanja": "搂", "um": "lǒu"},
{"hanja": "惠", "um": "huì"},
{"hanja": "溢", "um": "yì"},
{"hanja": "杯", "um": "bēi"},
{"hanja": "膏", "um": "gāo"},
{"hanja": "竿", "um": "gān"},
{"hanja": "杖", "um": "zhàng"},
{"hanja": "幽", "um": "yōu"},
{"hanja": "阴", "um": "yīn"},
{"hanja": "魂", "um": "hún"},
{"hanja": "缺", "um": "quē"},
{"hanja": "筋", "um": "jīn"},
{"hanja": "瘸", "um": "qué"},
{"hanja": "努", "um": "nǔ"},
{"hanja": "较", "um": "jiào"},
{"hanja": "扭", "um": "niǔ"},
{"hanja": "窝", "um": "wō"},
{"hanja": "黎", "um": "lí"},
{"hanja": "跤", "um": "jiāo"},
{"hanja": "摔", "um": "shuāi"},
{"hanja": "渡", "um": "dù"},
{"hanja": "博", "um": "bó"},
{"hanja": "解", "um": "jiě"},
{"hanja": "闲", "um": "xián"},
{"hanja": "驹", "um": "jū"},
{"hanja": "崽", "um": "zǎi"},
{"hanja": "脱", "um": "tuō"},
{"hanja": "剩", "um": "shèng"},
{"hanja": "兵", "um": "bīng"},
{"hanja": "鉴", "um": "jiàn"},
{"hanja": "杜", "um": "dù"},
{"hanja": "尔", "um": "ěr"},
{"hanja": "堆", "um": "duī"},
{"hanja": "碌", "um": "lù"},
{"hanja": "霜", "um": "shuāng"},
{"hanja": "赔", "um": "péi"},
{"hanja": "撕", "um": "sī"},
{"hanja": "具", "um": "jù"},
{"hanja": "犯", "um": "fàn"},
{"hanja": "斥", "um": "chì"},
{"hanja": "篓", "um": "lǒu"},
{"hanja": "驮", "um": "tuó"},
{"hanja": "搜", "um": "sōu"},
{"hanja": "昧", "um": "mèi"},
{"hanja": "愚", "um": "yú"},
{"hanja": "鼓", "um": "gǔ"},
{"hanja": "击", "um": "jī"},
{"hanja": "唱", "um": "chàng"},
{"hanja": "乐", "um": "lè"},
{"hanja": "欢", "um": "huān"},
{"hanja": "吞", "um": "tūn"},
{"hanja": "跳", "um": "tiào"},
{"hanja": "铱", "um": "yī"},
{"hanja": "改", "um": "gǎi"},
{"hanja": "耀", "um": "yào"},
{"hanja": "荣", "um": "róng"},
{"hanja": "弱", "um": "ruò"},
{"hanja": "瘦", "um": "shòu"},
{"hanja": "沟", "um": "gōu"},
{"hanja": "牡", "um": "mǔ"},
{"hanja": "牝", "um": "pìn"},
{"hanja": "插", "um": "chā"},
{"hanja": "槽", "um": "cáo"},
{"hanja": "剥", "um": "bāo"},
{"hanja": "枝", "um": "zhī "},
{"hanja": "枫", "um": "fēng"},
{"hanja": "杏", "um": "xìng"},
{"hanja": "杨", "um": "yáng"},
{"hanja": "杂", "um": "zá"},
{"hanja": "纹", "um": "wén"},
{"hanja": "偷", "um": "tōu"},
{"hanja": "查", "um": "chá"},
{"hanja": "步", "um": "bù"},
{"hanja": "乡", "um": "xiāng"},
{"hanja": "瑟", "um": "sè"},
{"hanja": "雇", "um": "gù"},
{"hanja": "茄", "um": "jiā"},
{"hanja": "幸", "um": "xìng"},
{"hanja": "冤", "um": "yuān"},
{"hanja": "膝", "um": "xī"},
{"hanja": "姊", "um": "zǐ"},
{"hanja": "毗", "um": "pí"},
{"hanja": "糠", "um": "kāng"},
{"hanja": "顺", "um": "shùn"},
{"hanja": "枯", "um": "kū"},
{"hanja": "溪", "um": "xī"},
{"hanja": "慢", "um": "màn"},
{"hanja": "亵", "um": "xiè"},
{"hanja": "谋", "um": "móu"},
{"hanja": "计", "um": "jì"},
{"hanja": "赞", "um": "zàn"},
{"hanja": "缅", "um": "miǎn"},
{"hanja": "宠", "um": "chǒng"},
{"hanja": "失", "um": "shī"},
{"hanja": "辟", "um": "bì"},
{"hanja": "矩", "um": "jǔ"},
{"hanja": "悉", "um": "xī"},
{"hanja": "深", "um": "shēn"},
{"hanja": "秀", "um": "xiù"},
{"hanja": "由", "um": "yóu"},
{"hanja": "甥", "um": "shēng"},
{"hanja": "识", "um": "shí"},
{"hanja": "集", "um": "jí"},
{"hanja": "饮", "um": "yǐn"},
{"hanja": "浇", "um": "jiāo"},
{"hanja": "殿", "um": "diàn"},
{"hanja": "弃", "um": "qì"},
{"hanja": "展", "um": "zhǎn"},
{"hanja": "梯", "um": "tī"},
{"hanja": "卧", "um": "wò"},
{"hanja": "枕", "um": "zhěn"},
{"hanja": "舅", "um": "jiù"},
{"hanja": "嘱", "um": "zhǔ"},
{"hanja": "厌", "um": "yàn"},
{"hanja": "忘", "um": "wàng"},
{"hanja": "雪", "um": "xuě"},
{"hanja": "丧", "um": "sàng"},
{"hanja": "怨", "um": "yuàn"},
{"hanja": "轭", "um": "è"},
{"hanja": "挣", "um": "zhèng"},
{"hanja": "倚", "um": "yǐ"},
{"hanja": "骗", "um": "piàn"},
{"hanja": "痛", "um": "tòng"},
{"hanja": "兢", "um": "jīng"},
{"hanja": "甘", "um": "gān"},
{"hanja": "递", "um": "dì"},
{"hanja": "辨", "um": "biàn"},
{"hanja": "挨", "um": "āi"},
{"hanja": "快", "um": "kuài"},
{"hanja": "项", "um": "xiàng"},
{"hanja": "颈", "um": "jǐng"},
{"hanja": "招", "um": "zhāo"},
{"hanja": "哄", "um": "hōng"},
{"hanja": "滑", "um": "huá"},
{"hanja": "肥", "um": "féi"},
{"hanja": "囊", "um": "náng"},
{"hanja": "械", "um": "xiè"},
{"hanja": "烦", "um": "fán"},
{"hanja": "伦", "um": "lún"},
{"hanja": "滴", "um": "dī"},
{"hanja": "恨", "um": "hèn"},
{"hanja": "友", "um": "yǒu"},
{"hanja": "朋", "um": "péng"},
{"hanja": "阔", "um": "kuò"},
{"hanja": "竞", "um": "jìng"},
{"hanja": "填", "um": "tián"},
{"hanja": "妒", "um": "dù"},
{"hanja": "嫉", "um": "jí"},
{"hanja": "险", "um": "xiǎn"},
{"hanja": "麽", "um": "me"},
{"hanja": "玩", "um": "wán"},
{"hanja": "久", "um": "jiǔ"},
{"hanja": "例", "um": "lì"},
{"hanja": "轻", "um": "qīng"},
{"hanja": "豆", "um": "dòu"},
{"hanja": "累", "um": "lèi"},
{"hanja": "汤", "um": "tāng"},
{"hanja": "熬", "um": "áo"},
{"hanja": "味", "um": "wèi"},
{"hanja": "静", "um": "jìng"},
{"hanja": "抓", "um": "zhuā"},
{"hanja": "扫", "um": "sǎo"},
{"hanja": "毛", "um": "máo"},
{"hanja": "浑", "um": "hún"},
{"hanja": "双", "um": "shuāng"},
{"hanja": "腹", "um": "fù"},
{"hanja": "祈", "um": "qí"},
{"hanja": "寨", "um": "zhài"},
{"hanja": "营", "um": "yíng"},
{"hanja": "庄", "um": "zhuāng"},
{"hanja": "村", "um": "cūn"},
{"hanja": "突", "um": "tū"},
{"hanja": "衫", "um": "shān"},
{"hanja": "谱", "um": "pǔ"},
{"hanja": "趁", "um": "chèn"},
{"hanja": "庶", "um": "shù"},
{"hanja": "珊", "um": "shān"},
{"hanja": "办", "um": "bàn"},
{"hanja": "铅", "um": "qiān"},
{"hanja": "默", "um": "mò"},
{"hanja": "刚", "um": "gāng"},
{"hanja": "骑", "um": "qí"},
{"hanja": "误", "um": "wù"},
{"hanja": "耽", "um": "dān"},
{"hanja": "让", "um": "ràng"},
{"hanja": "宝", "um": "bǎo"},
{"hanja": "歹", "um": "dǎi"},
{"hanja": "导", "um": "dǎo"},
{"hanja": "戴", "um": "dài"},
{"hanja": "白", "um": "bái"},
{"hanja": "饭", "um": "fàn"},
{"hanja": "喂", "um": "wèi"},
{"hanja": "卸", "um": "xiè"},
{"hanja": "拾", "um": "shí"},
{"hanja": "收", "um": "shōu"},
{"hanja": "班", "um": "bān"},
{"hanja": "诚", "um": "chéng"},
{"hanja": "宿", "um": "sù"},
{"hanja": "镯", "um": "zhuó"},
{"hanja": "句", "um": "jù"},
{"hanja": "槽", "um": "cáo"},
{"hanja": "扛", "um": "káng"},
{"hanja": "瓶", "um": "píng"},
{"hanja": "机", "um": "jī"},
{"hanja": "跪", "um": "guì"},
{"hanja": "索", "um": "suǒ"},
{"hanja": "匹", "um": "pǐ"},
{"hanja": "干", "um": "gàn"},
{"hanja": "遣", "um": "qiǎn"},
{"hanja": "慎", "um": "shèn"},
{"hanja": "谨", "um": "jǐn"},
{"hanja": "麽", "um": "ma"},
{"hanja": "肯", "um": "kěn"},
{"hanja": "倘", "um": "tǎng"},
{"hanja": "腿", "um": "tuǐ"},
{"hanja": "藉", "um": "jiè"},
{"hanja": "妥", "um": "tuǒ"},
{"hanja": "准", "um": "zhǔn"},
{"hanja": "客", "um": "kè"},
{"hanja": "值", "um": "zhí"},
{"hanja": "卖", "um": "mài"},
{"hanja": "价", "um": "jià"},
{"hanja": "坟", "um": "fén"},
{"hanja": "最", "um": "zuì"},
{"hanja": "尊", "um": "zūn"},
{"hanja": "恸", "um": "tòng"},
{"hanja": "益", "um": "yì"},
{"hanja": "薛", "um": "Xuē"},
{"hanja": "稠", "um": "chóu"},
{"hanja": "扣", "um": "kòu"},
{"hanja": "角", "um": "jiǎo"},
{"hanja": "畏", "um": "wèi"},
{"hanja": "敬", "um": "jìng"},
{"hanja": "绑", "um": "bǎng"},
{"hanja": "捆", "um": "kǔn"},
{"hanja": "刀", "um": "dāo"},
{"hanja": "柴", "um": "chái"},
{"hanja": "验", "um": "yàn"},
{"hanja": "试", "um": "shì"},
{"hanja": "柳", "um": "liǔ"},
{"hanja": "丝", "um": "sī"},
{"hanja": "垂", "um": "chuí"},
{"hanja": "挖", "um": "wā"},
{"hanja": "羔", "um": "gāo"},
{"hanja": "责", "um": "zé"},
{"hanja": "占", "um": "zhàn"},
{"hanja": "霸", "um": "bà"},
{"hanja": "负", "um": "fù"},
{"hanja": "欺", "um": "qī"},
{"hanja": "军", "um": "jūn"},
{"hanja": "弓", "um": "gōng"},
{"hanja": "佑", "um": "yòu"},
{"hanja": "抱", "um": "bào"},
{"hanja": "哭", "um": "kū"},
{"hanja": "忍", "um": "rěn"},
{"hanja": "箭", "um": "jiàn"},
{"hanja": "撇", "um": "piě"},
{"hanja": "袋", "um": "dài"},
{"hanja": "童", "um": "tóng"},
{"hanja": "愁", "um": "chóu"},
{"hanja": "丰", "um": "fēng"},
{"hanja": "婴", "um": "yīng"},
{"hanja": "乳", "um": "rǔ"},
{"hanja": "医", "um": "yī"},
{"hanja": "哨", "um": "shào"},
{"hanja": "千", "um": "qiān"},
{"hanja": "典", "um": "diǎn"},
{"hanja": "况", "um": "kuàng"},
{"hanja": "陷", "um": "xiàn"},
{"hanja": "竟", "um": "jìng"},
{"hanja": "祷", "um": "dǎo"},
{"hanja": "沾", "um": "zhān"},
{"hanja": "阻", "um": "zǔ"},
{"hanja": "梦", "um": "mèng"},
{"hanja": "扪", "um": "mén"},
{"hanja": "始", "um": "shǐ"},
{"hanja": "几", "um": "jǐ"},
{"hanja": "昨", "um": "zuó"},
{"hanja": "寝", "um": "qǐn"},
{"hanja": "规", "um": "guī"},
{"hanja": "常", "um": "cháng"},
{"hanja": "洞", "um": "dòng"},
{"hanja": "般", "um": "bān"},
{"hanja": "窑", "um": "yáo"},
{"hanja": "删", "um": "shān"},
{"hanja": "柱", "um": "zhù"},
{"hanja": "磺", "um": "huáng"},
{"hanja": "硫", "um": "liú"},
{"hanja": "覆", "um": "fù"},
{"hanja": "倾", "um": "qīng"},
{"hanja": "易", "um": "yì"},
{"hanja": "祸", "um": "huò"},
{"hanja": "性", "um": "xìng"},
{"hanja": "救", "um": "jiù"},
{"hanja": "慈", "um": "cí"},
{"hanja": "恤", "um": "xù"},

{"hanja": "怜", "um": "lián"},
{"hanja": "延", "um": "yán"},
{"hanja": "迟", "um": "chí"},
{"hanja": "逼", "um": "bī"},
{"hanja": "催", "um": "cuī"},
{"hanja": "戏", "um": "xì"},
{"hanja": "差", "um": "chà"},
{"hanja": "内", "um": "nèi"},
{"hanja": "婿", "um": "xù"},
{"hanja": "寻", "um": "xún"},
{"hanja": "总", "um": "zǒng"},
{"hanja": "迷", "um": "mí"},
{"hanja": "昏", "um": "hūn"},
{"hanja": "破", "um": "pò"},

{"hanja": "挤", "um": "jǐ"},
{"hanja": "拥", "um": "yōng"},
{"hanja": "官", "um": "guān"},
{"hanja": "舍", "um": "shè"},
{"hanja": "围", "um": "wéi"},
{"hanja": "躺", "um": "tǎng"},
{"hanja": "酵", "um": "jiào"},
{"hanja": "烤", "um": "kǎo"},
{"hanja": "席", "um": "xí"},
{"hanja": "筵", "um": "yán"},
{"hanja": "屋", "um": "wū"},
{"hanja": "街", "um": "jiē"},
{"hanja": "清", "um": "qīng"},
{"hanja": "拜", "um": "bài"},

{"hanja": "次", "um": "cì"},
{"hanja": "短", "um": "duǎn"},
{"hanja": "敢", "um": "gǎn"},
{"hanja": "虽", "um": "suī"},
{"hanja": "审", "um": "shěn"},
{"hanja": "恕", "um": "shù"},
{"hanja": "饶", "um": "ráo"},
{"hanja": "假", "um": "jiǎ"},
{"hanja": "剿", "um": "chāo"},
{"hanja": "旧", "um": "jiù"},
{"hanja": "察", "um": "chá"},
{"hanja": "秉", "um": "bǐng"},
{"hanja": "眷", "um": "juàn"},
{"hanja": "瞒", "um": "mán"},

{"hanja": "程", "um": "chéng"},
{"hanja": "认", "um": "rèn"},
{"hanja": "期", "um": "qī"},
{"hanja": "难", "um": "nán"},
{"hanja": "衰", "um": "shuāi"},
{"hanja": "迈", "um": "mài"},
{"hanja": "纪", "um": "jì"},
{"hanja": "位", "um": "wèi"},
{"hanja": "问", "um": "wèn"},
{"hanja": "奶", "um": "nǎi"},
{"hanja": "备", "um": "bèi"},
{"hanja": "预", "um": "yù"},
{"hanja": "犊", "um": "dú"},
{"hanja": "嫩", "um": "nèn"},

{"hanja": "牵", "um": "qiān"},
{"hanja": "调", "um": "diào"},
{"hanja": "速", "um": "sù"},
{"hanja": "忙", "um": "máng"},
{"hanja": "急", "um": "jí"},
{"hanja": "添", "um": "tiān"},
{"hanja": "点", "um": "diǎn"},
{"hanja": "站", "um": "zhàn"},
{"hanja": "坐", "um": "zuò"},
{"hanja": "热", "um": "rè"},
{"hanja": "升", "um": "shēng"},
{"hanja": "允", "um": "yǔn"},
{"hanja": "笑", "um": "xiào"},
{"hanja": "剪", "um": "jiǎn"},

{"hanja": "须", "um": "xū"},
{"hanja": "买", "um": "mǎi"},
{"hanja": "据", "um": "jū"},
{"hanja": "证", "um": "zhèng"},
{"hanja": "阳", "um": "yáng"},
{"hanja": "礼", "um": "lǐ"},
{"hanja": "割", "um": "gē"},
{"hanja": "坚", "um": "jiān"},
{"hanja": "君", "um": "jūn"},
{"hanja": "度", "um": "dù"},
{"hanja": "罕", "um": "hǎn"},
{"hanja": "俯", "um": "fǔ"},
{"hanja": "庇", "um": "bì"},
{"hanja": "井", "um": "jǐng"},

{"hanja": "顾", "um": "gù"},
{"hanja": "情", "um": "qíng"},
{"hanja": "胜", "um": "shèng"},
{"hanja": "书", "um": "shū"},
{"hanja": "断", "um": "duàn"},
{"hanja": "判", "um": "pàn"},
{"hanja": "屈", "um": "qū"},
{"hanja": "妾", "um": "qiè"},
{"hanja": "者", "um": "zhě"},
{"hanja": "块", "um": "kuài"},
{"hanja": "炉", "um": "lú"},
{"hanja": "烟", "um": "yān"},
{"hanja": "冒", "um": "mào"},
{"hanja": "料", "um": "liào"},

{"hanja": "盈", "um": "yíng"},
{"hanja": "孽", "um": "niè"},
{"hanja": "葬", "um": "zàng"},
{"hanja": "埋", "um": "mái"},
{"hanja": "寿", "um": "shòu"},
{"hanja": "享", "um": "xiǎng"},
{"hanja": "惩", "um": "chéng"},
{"hanja": "寄", "um": "jì"},
{"hanja": "确", "um": "què"},
{"hanja": "忽", "um": "hū"},
{"hanja": "吓", "um": "hè"},
{"hanja": "鸷", "um": "zhì"},
{"hanja": "半", "um": "bàn"},
{"hanja": "劈", "um": "pī"},

{"hanja": "雏", "um": "chú"},
{"hanja": "鸠", "um": "jiū"},
{"hanja": "斑", "um": "bān"},
{"hanja": "绵", "um": "mián"},
{"hanja": "信", "um": "xìn"},
{"hanja": "嗣", "um": "sì"},
{"hanja": "谢", "um": "xiè"},
{"hanja": "业", "um": "yè"},
{"hanja": "承", "um": "chéng"},
{"hanja": "赏", "um": " shǎng"},
{"hanja": "牌", "um": "pái"},
{"hanja": "盾", "um": "dùn"},
{"hanja": "象", "um": "xiàng"},
{"hanja": "异", "um": "yì"},

{"hanja": "凭", "um": "píng"},
{"hanja": "任", "um": "rèn"},
{"hanja": "足", "um": "zú"},
{"hanja": "富", "um": "fù"},
{"hanja": "鞋", "um": "xié"},
{"hanja": "线", "um": "xiàn"},

{"hanja": "根", "um": "gēn"},
{"hanja": "誓", "um": "shì"},
{"hanja": "主", "um": "zhǔ"},
{"hanja": "司", "um": "sī"},
{"hanja": "饼", "um": "bǐng"},
{"hanja": "冷", "um": "lěng"},
{"hanja": "迎", "um": "yíng"},
{"hanja": "夺", "um": "duó"},
{"hanja": "敌", "um": "dí"},
{"hanja": "队", "um": "duì"},
{"hanja": "追", "um": "zhuī"},
{"hanja": "丁", "um": "dīng"},
{"hanja": "练", "um": "liàn"},
{"hanja": "精", "um": "jīng"},
{"hanja": "率", "um": "shuài"},
{"hanja": "联", "um": "lián"},
{"hanja": "掠", "um": "lüè"},
{"hanja": "掳", "um": "lǔ"},
{"hanja": "粮", "um": "liáng"},
{"hanja": "馀", "um": "yú"},

{"hanja": "掉", "um": "diào"},
{"hanja": "跑", "um": "pǎo"},
{"hanja": "逃", "um": "táo"},
{"hanja": "坑", "um": "kēng"},
{"hanja": "战", "um": "zhàn"},
{"hanja": "阵", "um": "zhèn"},
{"hanja": "旷", "um": "kuàng"},
{"hanja": "靠", "um": "kào"},
{"hanja": "何", "um": "hé"},
{"hanja": "亭", "um": "tíng"},
{"hanja": "苏", "um": "sū"},
{"hanja": "乏", "um": "fá"},
{"hanja": "律", "um": "lǜ"},
{"hanja": "盟", "um": "méng"},
{"hanja": "叛", "um": "pàn"},
{"hanja": "奉", "um": "fèng"},
{"hanja": "盐", "um": "yán"},
{"hanja": "会", "um": "huì"},
{"hanja": "谷", "um": "gǔ"},
{"hanja": "订", "um": "dìng"},

{"hanja": "攻", "um": "gōng"},
{"hanja": "印", "um": "yìn"},
{"hanja": "戈", "um": "gē"},
{"hanja": "达", "um": "dá"},
{"hanja": "略", "um": "lüè"},
{"hanja": "王", "um": "wáng"},
{"hanja": "幔", "um": "màn"},
{"hanja": "仑", "um": "lún"},
{"hanja": "搬", "um": "bān"},
{"hanja": "横", "um": "héng"},
{"hanja": "纵", "um": "zòng"},
{"hanja": "算", "um": "suàn"},
{"hanja": "数", "um": "shǔ"},
{"hanja": "北", "um": "běi"},
{"hanja": "邑", "um": "yì"},
{"hanja": "择", "um": "zé"},
{"hanja": "琐", "um": "suǒ"},
{"hanja": "旦", "um": "dàn"},
{"hanja": "举", "um": "jǔ"},
{"hanja": "右", "um": "yòu"},

{"hanja": "左", "um": "zuǒ"},
{"hanja": "请", "um": "qǐng"},
{"hanja": "文", "um": "wén"},
{"hanja": "争", "um": "zhēng"},
{"hanja": "银", "um": "yín"},
{"hanja": "送", "um": "sòng"},
{"hanja": "召", "um": "zhào"},
{"hanja": "灾", "um": "zāi"},
{"hanja": "婢", "um": "bì"},
{"hanja": "驴", "um": "lǘ"},
{"hanja": "驼", "um": "tuó"},
{"hanja": "骆", "um": "luò"},
{"hanja": "牛", "um": "niú"},
{"hanja": "待", "um": "dài"},
{"hanja": "厚", "um": "hòu"},
{"hanja": "宫", "um": "gōng"},
{"hanja": "奖", "um": "jiǎng"},
{"hanja": "夸", "um": "kuā"},
{"hanja": "宰", "um": "zǎi"},
{"hanja": "臣", "um": "chén"},

{"hanja": "老", "um": "lǎo"},
{"hanja": "俊", "um": "jùn"},
{"hanja": "容", "um": "róng"},
{"hanja": "近", "um": "jìn"},
{"hanja": "暂", "um": "zàn"},
{"hanja": "埃", "um": "āi"},
{"hanja": "荒", "um": "huāng"},
{"hanja": "饥", "um": "jī"},
{"hanja": "艾", "um": "ài"},
{"hanja": "显", "um": "xiǎn"},
{"hanja": "橡", "um": "xiàng"},
{"hanja": "财", "um": "cái"},
{"hanja": "侄", "um": "zhí"},
{"hanja": "祝", "um": "zhù"},
{"hanja": "指", "um": "zhǐ"},
{"hanja": "孩", "um": "hái"},
{"hanja": "育", "um": "yù"},
{"hanja": "亦", "um": "yì"},
{"hanja": "密", "um": "mì"},
{"hanja": "莱", "um": "lái"},

{"hanja": "先", "um": "xiān"},
{"hanja": "珥", "um": "ěr"},
{"hanja": "吾", "um": "wú"},
{"hanja": "罗", "um": "luó"},
{"hanja": "鹤", "um": "hè"},
{"hanja": "鹿", "um": "lù"},
{"hanja": "吴", "um": "wú"},
{"hanja": "乱", "um": "luàn"},
{"hanja": "民", "um": "mín"},
{"hanja": "临", "um": "lín"},
{"hanja": "扬", "um": "yáng"},
{"hanja": "传", "um": "chuán"},
{"hanja": "通", "um": "tōng"},
{"hanja": "塔", "um": "tǎ"},
{"hanja": "泥", "um": "nì"},
{"hanja": "灰", "um": "huī"},
{"hanja": "漆", "um": "qī"},
{"hanja": "石", "um": "shí"},
{"hanja": "烧", "um": "shāo"},
{"hanja": "砖", "um": "zhuān"},

{"hanja": "吧", "um": "ba"},
{"hanja": "量", "um": "liáng"},
{"hanja": "商", "um": "shāng"},
{"hanja": "原", "um": "yuán"},
{"hanja": "平", "um": "píng"},
{"hanja": "片", "um": "piàn"},
{"hanja": "移", "um": "yí"},
{"hanja": "迁", "um": "qiān"},
{"hanja": "派", "um": "pài"},
{"hanja": "支", "um": "zhī"},
{"hanja": "阿", "um": "ā"},
{"hanja": "俄", "um": "é"},
{"hanja": "答", "um": "dá"},
{"hanja": "坍", "um": "tān"},
{"hanja": "帖", "um": "tiě"},
{"hanja": "兰", "um": "lán"},
{"hanja": "德", "um": "dé"},
{"hanja": "拦", "um": "lán"},
{"hanja": "孙", "um": "sūn"},
{"hanja": "哥", "um": "gē"},

{"hanja": "邦", "um": "bāng"},
{"hanja": "扁", "um": "biǎn"},
{"hanja": "押", "um": "yā"},
{"hanja": "蛾", "um": "é"},
{"hanja": "萨", "um": "sà"},
{"hanja": "耳", "um": "ěr"},
{"hanja": "境", "um": "jìng"},
{"hanja": "马", "um": "mǎ"},
{"hanja": "瓦", "um": "wǎ"},
{"hanja": "未", "um": "wèi"},
{"hanja": "革", "um": "gé"},
{"hanja": "摩", "um": "mó"},
{"hanja": "布", "um": "bù"},
{"hanja": "赫", "um": "hè"},
{"hanja": "顿", "um": "dùn"},
{"hanja": "托", "um": "tuō"},
{"hanja": "鲁", "um": "lǔ"},
{"hanja": "斯", "um": "sī"},
{"hanja": "帕", "um": "pà"},
{"hanja": "希", "um": "xī"},

{"hanja": "低", "um": "dī"},
{"hanja": "鲜", "um": "xiān"},
{"hanja": "微", "um": "wēi"},
{"hanja": "尼", "um": "ní"},
{"hanja": "甲", "um": "jiǎ"},
{"hanja": "俗", "um": "sú"},
{"hanja": "猎", "um": "liè"},
{"hanja": "勇", "um": "yǒng"},
{"hanja": "首", "um": "shǒu"},
{"hanja": "雄", "um": "xióng"},
{"hanja": "录", "um": "lù"},
{"hanja": "宁", "um": "níng"},
{"hanja": "示", "um": "shì"},
{"hanja": "族", "um": "zú"},
{"hanja": "宗", "um": "zōng"},
{"hanja": "言", "um": "yán"},
{"hanja": "岛", "um": "dǎo"},
{"hanja": "国", "um": "guó"},
{"hanja": "单", "um": "dān"},
{"hanja": "施", "um": "shī"},

{"hanja": "沙", "um": "shā"},
{"hanja": "陀", "um": "tuó"},
{"hanja": "提", "um": "tí"},
{"hanja": "巴", "um": "bā"},
{"hanja": "篾", "um": "miè"},
{"hanja": "张", "um": "zhāng"},
{"hanja": "扩", "um": "kuò"},
{"hanja": "愿", "um": "yuàn"},
{"hanja": "颂", "um": "sòng"},
{"hanja": "应", "um": "yìng"},
{"hanja": "仆", "um": "pú"},
{"hanja": "奴", "um": "nú"},
{"hanja": "醒", "um": "xǐng"},
{"hanja": "背", "um": "bèi"},
{"hanja": "倒", "um": "dào"},
{"hanja": "肩", "um": "jiān"},
{"hanja": "搭", "um": "dā"},
{"hanja": "件", "um": "jiàn"},
{"hanja": "醉", "um": "zuì"},
{"hanja": "酒", "um": "jiǔ"},

{"hanja": "喝", "um": "hē"},
{"hanja": "萄", "um": "táo"},
{"hanja": "葡", "um": "pú"},
{"hanja": "栽", "um": "zāi"},
{"hanja": "农", "um": "nóng"},
{"hanja": "散", "um": "sǎn"},
{"hanja": "亲", "um": "qīn"},
{"hanja": "迦", "um": "jiā"},
{"hanja": "彩", "um": "cǎi"},
{"hanja": "云", "um": "yún"},
{"hanja": "虹", "um": "hóng"},
{"hanja": "绝", "um": "jué"},
{"hanja": "谕", "um": "yù"},
{"hanja": "晓", "um": "xiǎo"},
{"hanja": "茂", "um": "mào"},
{"hanja": "盛", "um": "shèng"},
{"hanja": "昌", "um": "chāng"},
{"hanja": "讨", "um": "tǎo"},
{"hanja": "论", "um": "lùn"},
{"hanja": "付", "um": "fù"},

{"hanja": "惧", "um": "jù"},
{"hanja": "惊", "um": "jīng"},
{"hanja": "冬", "um": "dōng"},
{"hanja": "暑", "um": "shǔ"},
{"hanja": "寒", "um": "hán"},
{"hanja": "穑", "um": "sè"},
{"hanja": "稼", "um": "jià"},
{"hanja": "存", "um": "cún"},
{"hanja": "馨", "um": "xīn"},
{"hanja": "闻", "um": "wén"},
{"hanja": "祭", "um": "jì"},
{"hanja": "燔", "um": "fán"},
{"hanja": "坛", "um": "tán"},
{"hanja": "筑", "um": "zhù"},
{"hanja": "旺", "um": "wàng"},
{"hanja": "兴", "um": "xīng"},
{"hanja": "盖", "um": "gài"},
{"hanja": "撤", "um": "chè"},
{"hanja": "榄", "um": "lǎn"},
{"hanja": "橄", "um": "gǎn"},

{"hanja": "拧", "um": "nǐng"},
{"hanja": "新", "um": "xīn"},
{"hanja": "叼", "um": "diāo"},
{"hanja": "嘴", "um": "zuǐ"},
{"hanja": "等", "um": "děng"},
{"hanja": "回", "um": "huí"},
{"hanja": "找", "um": "zhǎo"},
{"hanja": "鸽", "um": "gē"},
{"hanja": "乾", "um": "qián"},
{"hanja": "鸦", "um": "yā"},
{"hanja": "乌", "um": "wū"},
{"hanja": "放", "um": "fàng"},
{"hanja": "顶", "um": "dǐng"},
{"hanja": "腊", "um": "xī"},
{"hanja": "停", "um": "tíng"},
{"hanja": "消", "um": "xiāo"},
{"hanja": "退", "um": "tuì"},
{"hanja": "止", "um": "zhǐ"},
{"hanja": "闭", "um": "bì"},
{"hanja": "落", "um": "luò"},

{"hanja": "渐", "um": "jiān"},
{"hanja": "念", "um": "niàn"},
{"hanja": "岭", "um": "lǐng"},
{"hanja": "山", "um": "shān"},
{"hanja": "淹", "um": "yān"},
{"hanja": "极", "um": "jí"},
{"hanja": "浩", "um": "hào"},
{"hanja": "势", "um": "shì"},
{"hanja": "往", "um": "wǎng"},
{"hanja": "漂", "um": "piāo"},
{"hanja": "关", "um": "guān"},
{"hanja": "禽", "um": "qín"},
{"hanja": "敞", "um": "chǎng"},
{"hanja": "窗", "um": "chuāng"},
{"hanja": "裂", "um": "liè"},
{"hanja": "源", "um": "yuán"},
{"hanja": "泉", "um": "quán"},
{"hanja": "月", "um": "yuè"},
{"hanja": "整", "um": "zhěng"},
{"hanja": "遵", "um": "zūn"},

{"hanja": "净", "um": "jìng"},
{"hanja": "洁", "um": "jié"},
{"hanja": "家", "um": "jiā"},
{"hanja": "蓄", "um": "xù"},
{"hanja": "积", "um": "jī"},
{"hanja": "保", "um": "bǎo"},
{"hanja": "公", "um": "gōng"},
{"hanja": "每", "um": "měi"},
{"hanja": "入", "um": "rù"},
{"hanja": "进", "um": "jìn"},
{"hanja": "妇", "um": "fù"},
{"hanja": "约", "um": "yuē"},
{"hanja": "滥", "um": "làn"},
{"hanja": "泛", "um": "fàn"},
{"hanja": "洪", "um": "hóng"},
{"hanja": "层", "um": "céng"},
{"hanja": "旁", "um": "páng"},
{"hanja": "透", "um": "tòu"},
{"hanja": "留", "um": "liú"},
{"hanja": "高", "um": "gāo"},

{"hanja": "宽", "um": "kuān"},
{"hanja": "肘", "um": "zhǒu"},
{"hanja": "法", "um": "fǎ"},
{"hanja": "香", "um": "xiāng"},
{"hanja": "松", "um": "sōng"},
{"hanja": "抹", "um": "mò"},
{"hanja": "外", "um": "wài"},
{"hanja": "舟", "um": "zhōu"},
{"hanja": "斐", "um": "fěi"},
{"hanja": "歌", "um": "gē"},
{"hanja": "毁", "um": "huǐ"},
{"hanja": "观", "um": "guàn"},
{"hanja": "暴", "um": "bào"},
{"hanja": "强", "um": "qiáng"},
{"hanja": "坏", "um": "huài"},
{"hanja": "败", "um": "bài"},
{"hanja": "界", "um": "jiè"},
{"hanja": "义", "um": "yì"},
{"hanja": "恩", "um": "ēn"},
{"hanja": "灭", "um": "miè"},

{"hanja": "除", "um": "chú"},
{"hanja": "及", "um": "jí"},
{"hanja": "忧", "um": "yōu"},
{"hanja": "心", "um": "xīn"},
{"hanja": "悔", "um": "huǐ"},
{"hanja": "尽", "um": "jìn"},
{"hanja": "想", "um": "xiǎng"},
{"hanja": "很", "um": "hěn"},
{"hanja": "武", "um": "wǔ"},
{"hanja": "英", "um": "yīng"},
{"hanja": "交", "um": "jiāo"},
{"hanja": "伟", "um": "wěi"},
{"hanja": "然", "um": "rán"},
{"hanja": "乎", "um": "hū"},
{"hanja": "属", "um": "shǔ"},
{"hanja": "选", "um": "xuǎn"},
{"hanja": "挑", "um": "tiāo"},
{"hanja": "貌", "um": "mào"},
{"hanja": "美", "um": "měi"},
{"hanja": "弗", "um": "fú"},

{"hanja": "含", "um": "hán"},
{"hanja": "闪", "um": "shǎn"},
{"hanja": "慰", "um": "wèi"},
{"hanja": "操", "um": "cào"},
{"hanja": "勒", "um": "lè"},
{"hanja": "南", "um": "nán"},
{"hanja": "零", "um": "líng"},
{"hanja": "九", "um": "jiǔ"},
{"hanja": "共", "um": "gòng"},
{"hanja": "世", "um": "shì"},
{"hanja": "百", "um": "bǎi"},
{"hanja": "被", "um": "bèi"},
{"hanja": "求", "um": "qiú"},
{"hanja": "候", "um": "hòu"},
{"hanja": "士", "um": "shì"},
{"hanja": "替", "um": "tì"},
{"hanja": "代", "um": "dài"},
{"hanja": "另", "um": "lìng"},
{"hanja": "特", "um": "tè"},
{"hanja": "塞", "um": "sāi"},

{"hanja": "十", "um": "shí"},
{"hanja": "损", "um": "sǔn"},
{"hanja": "少", "um": "shǎo"},
{"hanja": "壮", "um": "zhuàng"},
{"hanja": "语", "um": "yǔ"},
{"hanja": "细", "um": "xì"},
{"hanja": "妹", "um": "mèi"},
{"hanja": "匠", "um": "jiàng"},
{"hanja": "或", "um": "huò"},
{"hanja": "器", "um": "qì"},
{"hanja": "铁", "um": "tiě"},
{"hanja": "铜", "um": "tóng"},
{"hanja": "箫", "um": "xiāo"},
{"hanja": "琴", "um": "qín"},
{"hanja": "弹", "um": "tán"},
{"hanja": "犹", "um": "yóu"},
{"hanja": "师", "um": "shī"},
{"hanja": "祖", "um": "zǔ"},
{"hanja": "棚", "um": "péng"},
{"hanja": "帐", "um": "zhàng"},

{"hanja": "八", "um": "bā"},
{"hanja": "洗", "um": "xǐ"},
{"hanja": "娶", "um": "qǔ"},
{"hanja": "麦", "um": "mài"},
{"hanja": "撒", "um": "sǎ"},
{"hanja": "利", "um": "lì"},
{"hanja": "雅", "um": "yǎ"},
{"hanja": "户", "um": "hù"},
{"hanja": "米", "um": "mǐ"},
{"hanja": "城", "um": "chéng"},
{"hanja": "座", "um": "zuò"},
{"hanja": "建", "um": "jiàn"},
{"hanja": "诺", "um": "nuò"},
{"hanja": "挪", "um": "nuó"},
{"hanja": "住", "um": "zhù"},
{"hanja": "倍", "um": "bèi"},
{"hanja": "报", "um": "bào"},
{"hanja": "遭", "um": "zāo"},
{"hanja": "凡", "um": "fán"},
{"hanja": "致", "um": "zhì"},

{"hanja": "逐", "um": "zhú"},
{"hanja": "今", "um": "jīn"},
{"hanja": "过", "um": "guò"},
{"hanja": "重", "um": "zhòng"},
{"hanja": "太", "um": "tài"},
{"hanja": "罚", "um": "fá"},
{"hanja": "刑", "um": "xíng"},
{"hanja": "荡", "um": "dàng"},
{"hanja": "飘", "um": "piāo"},
{"hanja": "力", "um": "lì"},
{"hanja": "效", "um": "xiào"},
{"hanja": "再", "um": "zài"},
{"hanja": "接", "um": "jiē"},
{"hanja": "哀", "um": "āi"},
{"hanja": "向", "um": "xiàng"},
{"hanja": "血", "um": "xuè"},
{"hanja": "杀", "um": "shā"},
{"hanja": "正", "um": "zhèng"},
{"hanja": "制", "um": "zhì"},
{"hanja": "却", "um": "què"},

{"hanja": "门", "um": "mén"},
{"hanja": "伏", "um": "fú"},
{"hanja": "罪", "um": "zuì"},
{"hanja": "纳", "um": "nà"},
{"hanja": "蒙", "um": "méng"},
{"hanja": "若", "um": "ruò"},
{"hanja": "色", "um": "sè"},
{"hanja": "脸", "um": "liǎn"},
{"hanja": "变", "um": "biàn"},
{"hanja": "怒", "um": "nù"},
{"hanja": "油", "um": "yóu"},
{"hanja": "脂", "um": "zhī"},
{"hanja": "群", "um": "qún"},
{"hanja": "献", "um": "xiàn"},
{"hanja": "供", "um": "gòng"},
{"hanja": "羊", "um": "yáng"},
{"hanja": "牧", "um": "mù"},
{"hanja": "弟", "um": "dì"},
{"hanja": "兄", "um": "xiōng"},
{"hanja": "思", "um": "sī"},

{"hanja": "隐", "um": "yǐn"},
{"hanja": "该", "um": "gāi"},
{"hanja": "孕", "um": "yùn"},
{"hanja": "房", "um": "fáng"},
{"hanja": "剑", "um": "jiàn"},
{"hanja": "焰", "um": "yàn"},
{"hanja": "火", "um": "huǒ"},
{"hanja": "转", "um": "zhuàn"},
{"hanja": "路", "um": "lù"},
{"hanja": "设", "um": "shè"},
{"hanja": "赶", "um": "gǎn"},
{"hanja": "去", "um": "qù"},
{"hanja": "打", "um": "dǎ"},
{"hanja": "远", "um": "yuǎn"},

{"hanja": "永", "um": "yǒng"},
{"hanja": "手", "um": "shǒu"},
{"hanja": "伸", "um": "shēn"},
{"hanja": "恐", "um": "kǒng"},
{"hanja": "现", "um": "xiàn"},
{"hanja": "似", "um": "sì"},
{"hanja": "相", "um": "xiàng"},
{"hanja": "穿", "um": "chuān"},
{"hanja": "服", "um": "fú"},
{"hanja": "衣", "um": "yī"},
{"hanja": "皮", "um": "pí"},
{"hanja": "娃", "um": "wá"},
{"hanja": "夏", "um": "xià"},
{"hanja": "仍", "um": "réng"},

{"hanja": "本", "um": "běn"},
{"hanja": "而", "um": "ér"},
{"hanja": "归", "um": "guī"},
{"hanja": "直", "um": "zhí"},
{"hanja": "口", "um": "kǒu"},
{"hanja": "糊", "um": "hù"},
{"hanja": "汗", "um": "hàn"},
{"hanja": "藜", "um": "lí"},
{"hanja": "蒺", "um": "jí"},
{"hanja": "棘", "um": "jí"},
{"hanja": "荆", "um": "jīng"},
{"hanja": "劳", "um": "láo"},
{"hanja": "故", "um": "gù"},
{"hanja": "缘", "um": "yuán"},

{"hanja": "话", "um": "huà"},
{"hanja": "辖", "um": "xiá"},
{"hanja": "慕", "um": "mù"},
{"hanja": "恋", "um": "liàn"},
{"hanja": "儿", "um": "ér"},
{"hanja": "产", "um": "chǎn"},
{"hanja": "楚", "um": "chǔ"},
{"hanja": "苦", "um": "kǔ"},
{"hanja": "胎", "um": "tāi"},
{"hanja": "怀", "um": "huái"},
{"hanja": "增", "um": "zēng"},
{"hanja": "加", "um": "jiā"},
{"hanja": "脚", "um": "jiǎo"},
{"hanja": "伤", "um": "shāng"},

{"hanja": "裔", "um": "yì"},
{"hanja": "后", "um": "hòu"},
{"hanja": "仇", "um": "chóu"},
{"hanja": "彼", "um": "bǐ"},
{"hanja": "终", "um": "zhōng"},
{"hanja": "肚", "um": "dù"},
{"hanja": "诅", "um": "zǔ"},
{"hanja": "咒", "um": "zhòu"},
{"hanja": "受", "um": "shòu"},
{"hanja": "既", "um": "jì"},
{"hanja": "诱", "um": "yòu"},
{"hanja": "引", "um": "yǐn"},
{"hanja": "同", "um": "tóng"},
{"hanja": "非", "um": "fēi"},

{"hanja": "莫", "um": "mò"},
{"hanja": "呢", "um": "ne"},
{"hanja": "诉", "um": "sù"},
{"hanja": "告", "um": "gào"},
{"hanja": "谁", "um": "shéi"},
{"hanja": "怕", "um": "pà"},
{"hanja": "害", "um": "hài"},
{"hanja": "唤", "um": "huàn"},
{"hanja": "呼", "um": "hū"},
{"hanja": "避", "um": "bì"},
{"hanja": "躲", "um": "duǒ"},
{"hanja": "藏", "um": "cáng"},
{"hanja": "音", "um": "yīn"},
{"hanja": "声", "um": "shēng"},

{"hanja": "听", "um": "tīng"},
{"hanja": "风", "um": "fēng"},
{"hanja": "凉", "um": "liáng"},
{"hanja": "裙", "um": "qún"},
{"hanja": "编", "um": "biān"},
{"hanja": "叶", "um": "yè"},
{"hanja": "花", "um": "huā"},
{"hanja": "无", "um": "wú"},
{"hanja": "拿", "um": "ná"},
{"hanja": "才", "um": "cái"},
{"hanja": "丈", "um": "zhàng"},
{"hanja": "摘", "um": "zhāi"},
{"hanja": "慧", "um": "huì"},
{"hanja": "智", "um": "zhì"},

{"hanja": "爱", "um": "ài"},
{"hanja": "喜", "um": "xǐ"},
{"hanja": "能", "um": "néng"},
{"hanja": "如", "um": "rú"},
{"hanja": "亮", "um": "liàng"},
{"hanja": "睛", "um": "jīng"},
{"hanja": "知", "um": "zhī"},
{"hanja": "得", "um": "dé"},
{"hanja": "免", "um": "miǎn"},
{"hanja": "摸", "um": "mō"},
{"hanja": "曾", "um": "céng"},
{"hanja": "棵", "um": "kē"},
{"hanja": "许", "um": "xǔ"},
{"hanja": "麽", "um": "mó"},

{"hanja": "许", "um": "xǔ"},
{"hanja": "真", "um": "zhēn"},
{"hanja": "岂", "um": "qǐ"},
{"hanja": "猾", "um": "huá"},
{"hanja": "狡", "um": "jiǎo"},
{"hanja": "更", "um": "gèng"},
{"hanja": "蛇", "um": "shé"},
{"hanja": "惟", "um": "wéi"},
{"hanja": "耻", "um": "chǐ"},
{"hanja": "羞", "um": "xiū"},
{"hanja": "赤", "um": "chì"},
{"hanja": "夫", "um": "fū"},
{"hanja": "时", "um": "shí"},
{"hanja": "连", "um": "lián"},

{"hanja": "妻", "um": "qī"},
{"hanja": "与", "um": "yǔ"},
{"hanja": "母", "um": "mǔ"},
{"hanja": "父", "um": "fù"},
{"hanja": "离", "um": "lí"},
{"hanja": "此", "um": "cǐ"},
{"hanja": "跟", "um": "gēn"},
{"hanja": "她", "um": "tā"},
{"hanja": "领", "um": "lǐng"},
{"hanja": "身", "um": "shēn"},
{"hanja": "合", "um": "hé"},
{"hanja": "肉", "um": "ròu"},
{"hanja": "骨", "um": "gǔ"},
{"hanja": "肋", "um": "lèi"},

{"hanja": "条", "um": "tiáo"},
{"hanja": "取", "um": "qǔ"},
{"hanja": "睡", "um": "shuì"},
{"hanja": "沉", "um": "chén"},
{"hanja": "见", "um": "jiàn"},
{"hanja": "遇", "um": "yù"},
{"hanja": "便", "um": "biàn"},
{"hanja": "字", "um": "zì"},
{"hanja": "饲", "um": "sì"},
{"hanja": "怎", "um": "zěn"},
{"hanja": "么", "um": "me"},
{"hanja": "什", "um": "shén"},
{"hanja": "前", "um": "qián"},
{"hanja": "带", "um": "dài"},

{"hanja": "助", "um": "zhù"},
{"hanja": "帮", "um": "bāng"},
{"hanja": "偶", "um": "ǒu"},
{"hanja": "配", "um": "pèi"},
{"hanja": "居", "um": "jū"},
{"hanja": "独", "um": "dú"},
{"hanja": "死", "um": "sǐ"},
{"hanja": "必", "um": "bì"},
{"hanja": "不", "um": "bù"},
{"hanja": "只", "um": "zhī"},
{"hanja": "吃", "um": "chī"},
{"hanja": "意", "um": "yì"},
{"hanja": "随", "um": "suí"},
{"hanja": "咐", "um": "fù"},

{"hanja": "吩", "um": "fēn"},
{"hanja": "守", "um": "shǒu"},
{"hanja": "修", "um": "xiū"},
{"hanja": "伯", "um": "bó"},
{"hanja": "边", "um": "biān"},
{"hanja": "述", "um": "shù"},
{"hanja": "底", "um": "dǐ"},
{"hanja": "西", "um": "xī"},
{"hanja": "实", "um": "shí"},
{"hanja": "古", "um": "gǔ"},
{"hanja": "训", "um": "xùn"},
{"hanja": "基", "um": "jī"},
{"hanja": "瑙", "um": "nǎo"},
{"hanja": "玛", "um": "mǎ"},

{"hanja": "红", "um": "hóng"},
{"hanja": "珠", "um": "zhū"},
{"hanja": "珍", "um": "zhēn"},
{"hanja": "且", "um": "qiě"},
{"hanja": "金", "um": "jīn"},
{"hanja": "拉", "um": "lā"},
{"hanja": "腓", "um": "féi"},
{"hanja": "哈", "um": "hā"},
{"hanja": "绕", "um": "rào"},
{"hanja": "环", "um": "huán"},
{"hanja": "逊", "um": "xùn"},
{"hanja": "比", "um": "bǐ"},
{"hanja": "道", "um": "dào"},
{"hanja": "流", "um": "liú"},


{"hanja": "河", "um": "hé"},
{"hanja": "恶", "um": "è"},
{"hanja": "善", "um": "shàn"},
{"hanja": "目", "um": "mù"},
{"hanja": "眼", "um": "yǎn"},
{"hanja": "悦", "um": "yuè"},
{"hanja": "那", "um": "nà"},
{"hanja": "置", "um": "zhì"},
{"hanja": "园", "um": "yuán"},
{"hanja": "立", "um": "lì"},
{"hanja": "甸", "um": "diàn"},
{"hanja": "伊", "um": "yī"},
{"hanja": "方", "um": "fāng"},

{"hanja": "东", "um": "dōng"},
{"hanja": "当", "um": "dàng"},
{"hanja": "亚", "um": "yà"},
{"hanja": "叫", "um": "jiào"},
{"hanja": "名", "um": "míng"},
{"hanja": "孔", "um": "kǒng"},
{"hanja": "鼻", "um": "bí"},
{"hanja": "吹", "um": "chuī"},
{"hanja": "土", "um": "tǔ"},
{"hanja": "尘", "um": "chén"},

{"hanja": "用", "um": "yòng"},
{"hanja": "润", "um": "rùn"},
{"hanja": "腾", "um": "téng"},
{"hanja": "雾", "um": "wù"},
{"hanja": "但", "um": "dàn"},
{"hanja": "耕", "um": "gēng"},
{"hanja": "雨", "um": "yǔ"},
{"hanja": "降", "um": "jiàng"},
{"hanja": "长", "um": "cháng"},
{"hanja": "田", "um": "tián"},

{"hanja": "没", "um": "méi"},
{"hanja": "还", "um": "hái"},
{"hanja": "华", "um": "huá"},
{"hanja": "耶", "um": "yé"},
{"hanja": "历", "um": "lì"},
{"hanja": "因", "um": "yīn"},
{"hanja": "圣", "um": "shèng"},
{"hanja": "息", "um": "xī"},
{"hanja": "安", "um": "ān"},
{"hanja": "歇", "um": "xiē"},

{"hanja": "毕", "um": "bì"},
{"hanja": "完", "um": "wán"},
{"hanja": "经", "um": "jīng"},
{"hanja": "已", "um": "yǐ"},
{"hanja": "工", "um": "gōng"},
{"hanja": "七", "um": "qī"},
{"hanja": "到", "um": "dào"},
{"hanja": "齐", "um": "qí"},
{"hanja": "万", "um": "wàn"},
{"hanja": "六", "um": "liù"},

{"hanja": "甚", "um": "shén"},
{"hanja": "它", "um": "tā"},
{"hanja": "走", "um": "zǒu"},
{"hanja": "至", "um": "zhì"},
{"hanja": "食", "um": "shí"},
{"hanja": "你", "um": "nǐ"},
{"hanja": "哪", "um": "nǎ"},
{"hanja": "治", "um": "zhì"},
{"hanja": "遍", "um": "biàn"},
{"hanja": "养", "um": "yǎng"},

{"hanja": "对", "um": "duì"},
{"hanja": "女", "um": "nǚ"},
{"hanja": "男", "um": "nán"},
{"hanja": "乃", "um": "nǎi"},
{"hanja": "己", "um": "jǐ"},
{"hanja": "自", "um": "zì"},
{"hanja": "爬", "um": "pá"},
{"hanja": "全", "um": "quán"},
{"hanja": "里", "um": "lǐ"},
{"hanja": "他", "um": "tā"},

{"hanja": "人", "um": "rén"},
{"hanja": "式", "um": "shì"},
{"hanja": "按", "um": "àn"},
{"hanja": "像", "um": "xiàng"},
{"hanja": "形", "um": "xíng"},
{"hanja": "们", "um": "men"},
{"hanja": "我", "um": "wǒ"},
{"hanja": "兽", "um": "shòu"},
{"hanja": "野", "um": "yě"},
{"hanja": "虫", "um": "chóng"},

{"hanja": "昆", "um": "kūn"},
{"hanja": "畜", "um": "chù"},
{"hanja": "牲", "um": "shēng"},
{"hanja": "活", "um": "huó"},
{"hanja": "五", "um": "wǔ"},
{"hanja": "也", "um": "yě"},
{"hanja": "满", "um": "mǎn"},
{"hanja": "充", "um": "chōng"},
{"hanja": "繁", "um": "fán"},
{"hanja": "切", "um": "qiē"},

{"hanja": "雀", "um": "què"},
{"hanja": "鸟", "um": "niǎo"},
{"hanja": "飞", "um": "fēi"},
{"hanja": "中", "um": "zhōng"},
{"hanja": "给", "um": "gěi"},
{"hanja": "福", "um": "fú"},
{"hanja": "赐", "um": "cì"},
{"hanja": "动", "um": "dòng"},
{"hanja": "所", "um": "suǒ"},
{"hanja": "鱼", "um": "yú"},


{"hanja": "起", "um": "qǐ"},
{"hanja": "初", "um": "chū"},
{"hanja": "神", "um": "shén"},
{"hanja": "创", "um": "chuàng"},
{"hanja": "造", "um": "zào"},
{"hanja": "天", "um": "tiān"},
{"hanja": "地", "um": "dì"},
{"hanja": "是", "um": "shì"},
{"hanja": "空", "um": "kōng"},
{"hanja": "虚", "um": "xū"},

{"hanja": "混", "um": "hùn"},
{"hanja": "沌", "um": "dùn"},
{"hanja": "渊", "um": "yuān"},
{"hanja": "面", "um": "miàn"},
{"hanja": "黑", "um": "hēi"},
{"hanja": "暗", "um": "àn"},
{"hanja": "的", "um": "de"},
{"hanja": "灵", "um": "líng"},
{"hanja": "运", "um": "yùn"},
{"hanja": "行", "um": "xíng"},

{"hanja": "在", "um": "zài"},
{"hanja": "水", "um": "shuǐ"},
{"hanja": "上", "um": "shàng"},
{"hanja": "说", "um": "shuō"},
{"hanja": "要", "um": "yào"},
{"hanja": "有", "um": "yǒu"},
{"hanja": "光", "um": "guāng"},
{"hanja": "就", "um": "jiù"},
{"hanja": "了", "um": "le"},
{"hanja": "看", "um": "kàn"},

{"hanja": "好", "um": "hǎo"},
{"hanja": "把", "um": "bǎ"},
{"hanja": "分", "um": "fēn"},
{"hanja": "开", "um": "kāi"},
{"hanja": "称", "um": "chēng"},
{"hanja": "为", "um": "wèi"},
{"hanja": "昼", "um": "zhòu"},
{"hanja": "夜", "um": "yè"},
{"hanja": "晚", "um": "wǎn"},
{"hanja": "早", "um": "zǎo"},

{"hanja": "晨", "um": "chén"},
{"hanja": "这", "um": "zhè"},
{"hanja": "头", "um": "tóu"},
{"hanja": "一", "um": "yī"},
{"hanja": "日", "um": "rì"},
{"hanja": "诸", "um": "zhū"},
{"hanja": "之", "um": "zhī"},
{"hanja": "间", "um": "jiàn"},
{"hanja": "气", "um": "qì"},
{"hanja": "将", "um": "jiāng"},

{"hanja": "下", "um": "xià"},
{"hanja": "出", "um": "chū"},
{"hanja": "以", "um": "yǐ"},
{"hanja": "事", "um": "shì"},
{"hanja": "样", "um": "yàng"},
{"hanja": "成", "um": "chéng"},
{"hanja": "第", "um": "dì"},
{"hanja": "二", "um": "èr"},
{"hanja": "聚", "um": "jù"},
{"hanja": "处", "um": "chǔ"},

{"hanja": "使", "um": "shǐ"},
{"hanja": "旱", "um": "hàn"},
{"hanja": "露", "um": "lù"},
{"hanja": "来", "um": "lái"},
{"hanja": "海", "um": "hǎi"},
{"hanja": "发", "um": "fā"},
{"hanja": "生", "um": "shēng"},
{"hanja": "青", "um": "qīng"},
{"hanja": "草", "um": "cǎo"},
{"hanja": "和", "um": "hé"},

{"hanja": "结", "um": "jié"},
{"hanja": "种", "um": "zhǒng"},
{"hanja": "子", "um": "zǐ"},
{"hanja": "菜", "um": "cài"},
{"hanja": "蔬", "um": "shū"},
{"hanja": "并", "um": "bìng"},
{"hanja": "果", "um": "guǒ"},
{"hanja": "树", "um": "shù"},
{"hanja": "木", "um": "mù"},
{"hanja": "各", "um": "gè"},

{"hanja": "从", "um": "cóng"},
{"hanja": "其", "um": "qí"},
{"hanja": "类", "um": "lèi"},
{"hanja": "都", "um": "dōu"},
{"hanja": "包", "um": "bāo"},
{"hanja": "着", "um": "zhe"},
{"hanja": "核", "um": "hé"},
{"hanja": "于", "um": "yú"},
{"hanja": "三", "um": "sān"},
{"hanja": "体", "um": "tǐ"},

{"hanja": "可", "um": "kě"},
{"hanja": "作", "um": "zuò"},
{"hanja": "记", "um": "jì"},
{"hanja": "号", "um": "hào"},
{"hanja": "定", "um": "dìng"},
{"hanja": "节", "um": "jié"},
{"hanja": "令", "um": "lìng"},
{"hanja": "年", "um": "nián"},
{"hanja": "岁", "um": "suì"},
{"hanja": "普", "um": "pǔ"},

{"hanja": "照", "um": "zhào"},
{"hanja": "两", "um": "liǎng"},
{"hanja": "个", "um": "gè"},
{"hanja": "大", "um": "dà"},
{"hanja": "管", "um": "guǎn"},
{"hanja": "小", "um": "xiǎo"},
{"hanja": "又", "um": "yòu"},
{"hanja": "众", "um": "zhòng"},
{"hanja": "星", "um": "xīng"},
{"hanja": "些", "um": "xiē"},

{"hanja": "摆", "um": "bǎi"},
{"hanja": "列", "um": "liè"},
{"hanja": "理", "um": "lǐ"},
{"hanja": "别", "um": "bié"},
{"hanja": "明", "um": "míng"},
{"hanja": "四", "um": "sì"},
{"hanja": "多", "um": "duō"},
{"hanja": "滋", "um": "zī"},
{"hanja": "命", "um": "mìng"},
{"hanja": "物", "um": "wù"},

{"hanja": ".", "um": "."}

]}